{
    "book_number": 17,
    "book_name_am": "መጽሐፈ ዕዝራ",
    "book_short_name_am": "ዕዝ",
    "book_name_en": "Ezra",
    "book_short_name_en": "Ezr",
    "chapters": [
        {
            "chapter": 1,
            "sections": [
                {
                    "title": "አይ​ሁድ ወደ ሀገ​ራ​ቸው እን​ዲ​መ​ለሱ ቂሮስ እንደ ፈቀ​ደ​ላ​ቸው",
                    "verses": [
                        {
                            "verse": 1,
                            "text": "በኤ​ር​ም​ያስ አፍ የተ​ና​ገ​ረው የእ​ግ​ዚ​አ​ብ​ሔር ቃል ከተ​ፈ​ጸመ በኋላ በፋ​ርስ ንጉሥ በቂ​ሮስ በመ​ጀ​መ​ሪ​ያው ዓመት እግ​ዚ​አ​ብ​ሔር የፋ​ር​ስን ንጉሥ የቂ​ሮ​ስን መን​ፈስ አስ​ነሣ፤ እር​ሱም በመ​ን​ግ​ሥቱ ሁሉ አዋጅ አስ​ነ​ገረ፤ ደግ​ሞም በጽ​ሕ​ፈት እን​ዲህ አለ፦"
                        },
                        {
                            "verse": 2,
                            "text": "“የፋ​ርስ ንጉሥ ቂሮስ እን​ዲህ ይላል፦ የሰ​ማይ አም​ላክ እግ​ዚ​አ​ብ​ሔር የም​ድ​ርን መን​ግ​ሥ​ታት ሁሉ ሰጥ​ቶ​ኛል፤ በይ​ሁ​ዳም ባለ​ችው በኢ​የ​ሩ​ሳ​ሌም ቤትን እሠ​ራ​ለት ዘንድ እን​ዳ​ስብ አደ​ረ​ገኝ፤"
                        },
                        {
                            "verse": 3,
                            "text": "ከሕ​ዝቡ ሁሉ በእ​ና​ንተ ዘንድ ማንም ቢሆን አም​ላኩ ከእ​ርሱ ጋር ይሁን፤ እር​ሱም በይ​ሁዳ ወዳ​ለ​ችው ወደ ኢየ​ሩ​ሳ​ሌም ይውጣ፤ በኢ​የ​ሩ​ሳ​ሌ​ምም ለሚ​ኖ​ረው አም​ላክ፥ ለእ​ስ​ራ​ኤል አም​ላክ ለእ​ግ​ዚ​አ​ብ​ሔር ቤትን ይሥራ፤"
                        },
                        {
                            "verse": 4,
                            "text": "በስ​ደት በሚ​ኖ​ር​ባ​ቸው ከተ​ሞች ሁሉ ለቀ​ረው ሰው ሁሉ የሀ​ገሩ ሰዎች በብ​ርና በወ​ርቅ፥ በዕ​ቃም፥ በእ​ን​ስ​ሳም ይር​ዱት፤ ይህም በኢ​የ​ሩ​ሳ​ሌም ላለው ለእ​ግ​ዚ​አ​ብ​ሔር ቤት በፈ​ቃ​ዳ​ቸው ከሚ​ያ​ቀ​ር​ቡት ሌላ ይሁን።”"
                        },
                        {
                            "verse": 5,
                            "text": "የይ​ሁ​ዳና የብ​ን​ያም የአ​ባ​ቶች ቤቶች አለ​ቆ​ችም፥ ካህ​ና​ቱም፥ ሌዋ​ው​ያ​ኑም፥ በኢ​የ​ሩ​ሳ​ሌም ያለ​ውን የእ​ግ​ዚ​አ​ብ​ሔ​ርን ቤት ለመ​ሥ​ራት ይወጡ ዘንድ እግ​ዚ​አ​ብ​ሔር መን​ፈ​ሳ​ቸ​ውን ያነ​ሣ​ሣው ሁሉ ተነሡ።"
                        },
                        {
                            "verse": 6,
                            "text": "በዙ​ሪ​ያ​ቸ​ውም ያሉ ሁሉ በፈ​ቃ​ዳ​ቸው ካቀ​ረ​ቡት ሁሉ ሌላ በብር ዕቃና በወ​ርቅ፥ በገ​ን​ዘ​ቦ​ችና በእ​ን​ስ​ሶች፥ በሌ​ላም ስጦታ ይረ​ዷ​ቸው ነበር።"
                        },
                        {
                            "verse": 7,
                            "text": "ንጉሡ ቂሮ​ስም ናቡ​ከ​ደ​ነ​ፆር ከኢ​የ​ሩ​ሳ​ሌም ወስዶ በአ​ም​ላኩ"
                        },
                        {
                            "verse": 8,
                            "text": "የፋ​ርስ ንጉሥ ቂሮ​ስም የመ​ዝ​ገብ ሐላፊ በነ​በ​ረው በሚ​ት​ሪ​ዳጡ እጅ አወ​ጣ​ቸው፤ ለይ​ሁ​ዳም መስ​ፍን ለሲ​ሳ​ብ​ሳር ቈጠ​ራ​ቸው።"
                        },
                        {
                            "verse": 9,
                            "text": "ቍጥ​ራ​ቸ​ውም ይህ ነው፤ ሠላሳ የወ​ርቅ ሳሕ​ኖች፥ አንድ ሺህም የብር ሳሕ​ኖች፥ ሃያ ዘጠ​ኝም ቢላ​ዋ​ዎች፥ ሠላሳ የወ​ርቅ ዳካ​ዎች፥"
                        },
                        {
                            "verse": 10,
                            "text": "አራት መቶ ዐሥ​ርም ሌላ ዓይ​ነት የብር ዳካ​ዎች፥ አንድ ሺህም ሌላ ዕቃ ነበረ።"
                        },
                        {
                            "verse": 11,
                            "text": "የወ​ር​ቁና የብሩ ዕቃ​ዎች ሁሉ አም​ስት ሺህ አራት መቶ ነበሩ፤ እነ​ዚ​ህ​ንም ሁሉ ሲሳ​ብ​ሳር ከባ​ቢ​ሎን ወደ ኢየ​ሩ​ሳ​ሌም ከተ​መ​ለሱ ምር​ኮ​ኞች ጋር ወሰደ።"
                        }
                    ]
                }
            ]
        },
        {
            "chapter": 2,
            "sections": [
                {
                    "title": "ወደ ሀገ​ራ​ቸው የተ​መ​ለሱ የአ​ይ​ሁድ ስም ዝር​ዝር",
                    "verses": [
                        {
                            "verse": 1,
                            "text": "የባ​ቢ​ሎ​ንም ንጉሥ ናቡ​ከ​ደ​ነ​ፆር ወደ ባቢ​ሎን ከማ​ረ​ካ​ቸው ምር​ኮ​ኞች ወደ ኢየ​ሩ​ሳ​ሌ​ምና ወደ ይሁዳ፥ ወደ እየ​ከ​ተ​ማ​ቸው የተ​መ​ለ​ሱት የሀ​ገር ልጆች እነ​ዚህ ናቸው።"
                        },
                        {
                            "verse": 2,
                            "text": "ከዘ​ሩ​ባ​ቤል፥ ከኢ​ያሱ፥ ከነ​ህ​ምያ፥ ከሠ​ራያ፥ ከሮ​ሃ​ልያ፥ ከመ​ር​ዶ​ክ​ዮስ፥ ከበ​ላ​ሳን፥ ከመ​ሴ​ፋር፥ ከበ​ጎ​ዋይ፥ ከሬ​ሁም፥ ከበ​ዓና ጋር መጡ። የእ​ስ​ራ​ኤ​ልም ሕዝብ ሰዎች ቍጥር ይህ ነው፤"
                        },
                        {
                            "verse": 3,
                            "text": "የፋ​ሮስ ልጆች ሁለት ሺህ መቶ ሰባ ሁለት።"
                        },
                        {
                            "verse": 4,
                            "text": "የሰ​ፋ​ጥ​ያስ ልጆች ሦስት መቶ ሰባ ሁለት።"
                        },
                        {
                            "verse": 5,
                            "text": "የኤ​ራስ ልጆች ሰባት መቶ ሰባ አም​ስት።"
                        },
                        {
                            "verse": 6,
                            "text": "ከያ​ሱ​ኤና ከዮ​አብ ልጆች የሆ​ኑት የፈ​ሐት ሞዓብ ልጆች ሁለት ሺህ ስም​ንት መቶ ዐሥራ ሁለት።"
                        },
                        {
                            "verse": 7,
                            "text": "የኤ​ላም ልጆች ሺህ ሁለት መቶ አምሳ አራት።"
                        },
                        {
                            "verse": 8,
                            "text": "የዛ​ቱዕ ልጆች ዘጠኝ መቶ አርባ አም​ስት።"
                        },
                        {
                            "verse": 9,
                            "text": "የዘ​ካይ ልጆች ሰባት መቶ ስድሳ።"
                        },
                        {
                            "verse": 10,
                            "text": "የባኒ ልጆች ስድ​ስት መቶ አርባ ሁለት።"
                        },
                        {
                            "verse": 11,
                            "text": "የቢ​ባይ ልጆች ስድ​ስት መቶ ሃያ ሦስት።"
                        },
                        {
                            "verse": 12,
                            "text": "የዓ​ዝ​ጋድ ልጆች ሺህ ሁለት መቶ ሃያ ሁለት።"
                        },
                        {
                            "verse": 13,
                            "text": "የአ​ዶ​ኒ​ቃም ልጆች ስድ​ስት መቶ ስድሳ ስድ​ስት።"
                        },
                        {
                            "verse": 14,
                            "text": "የበ​ጕ​ዋይ ልጆች ሁለት ሺህ አምሳ ስድ​ስት።"
                        },
                        {
                            "verse": 15,
                            "text": "የዓ​ዲን ልጆች አራት መቶ አምሳ አራት።"
                        },
                        {
                            "verse": 16,
                            "text": "ከሕ​ዝ​ቅ​ያስ ወገን የአ​ጤር ልጆች ዘጠና ስም​ንት።"
                        },
                        {
                            "verse": 17,
                            "text": "የቤ​ሳይ ልጆች ሦስት መቶ ሃያ ሦስት።"
                        },
                        {
                            "verse": 18,
                            "text": "የዮራ ልጆች መቶ ዐሥራ ሁለት።"
                        },
                        {
                            "verse": 19,
                            "text": "የሐ​ሱም ልጆች ሁለት መቶ ሃያ ሦስት።"
                        },
                        {
                            "verse": 20,
                            "text": "የጋ​ቤር ልጆች ዘጠና አም​ስት።"
                        },
                        {
                            "verse": 21,
                            "text": "የቤተ ልሔም ልጆች መቶ ሃያ ሦስት።"
                        },
                        {
                            "verse": 22,
                            "text": "የነ​ጦፋ ልጆች አምሳ ስድ​ስት።"
                        },
                        {
                            "verse": 23,
                            "text": "የዓ​ና​ቶት ልጆች መቶ ሃያ ስም​ንት።"
                        },
                        {
                            "verse": 24,
                            "text": "የዓ​ዝ​ሞት ልጆች አርባ ሁለት።"
                        },
                        {
                            "verse": 25,
                            "text": "የቂ​ር​ያ​ት​ይ​ዓ​ሪ​ምና የቃ​ፌር፥ የብ​ኤ​ሮ​ትም ልጆች ሰባት መቶ አርባ ሦስት።"
                        },
                        {
                            "verse": 26,
                            "text": "የራ​ማና የጋ​ባዕ ልጆች ስድ​ስት መቶ ሃያ አንድ።"
                        },
                        {
                            "verse": 27,
                            "text": "የመ​ኪ​ማስ ሰዎች መቶ ሃያ ሁለት።"
                        },
                        {
                            "verse": 28,
                            "text": "የቤ​ቴ​ልና የጋይ ሰዎች ሁለት መቶ ሃያ ሦስት።"
                        },
                        {
                            "verse": 29,
                            "text": "የና​ባው ልጆች አምሳ ሁለት።"
                        },
                        {
                            "verse": 30,
                            "text": "የመ​ጌ​ባስ ልጆች መቶ አምሳ ስድ​ስት።"
                        },
                        {
                            "verse": 31,
                            "text": "የኤ​ላ​ማር ልጆች ሺህ ሁለት መቶ አምሳ አራት።"
                        },
                        {
                            "verse": 32,
                            "text": "የኤ​ላም ልጆች ሦስት መቶ ሃያ።"
                        },
                        {
                            "verse": 33,
                            "text": "የሎድ፥ የሐ​ዲ​ድና የኦ​ኖም ልጆች ሰባት መቶ ሃያ አም​ስት።"
                        },
                        {
                            "verse": 34,
                            "text": "የኢ​ያ​ሪኮ ልጆች ሦስት መቶ አርባ አም​ስት።"
                        },
                        {
                            "verse": 35,
                            "text": "የሴ​ዓ​ናህ ልጆች ሦስት ሺህ ስድ​ስት መቶ ሠላሳ።"
                        },
                        {
                            "verse": 36,
                            "text": "ካህ​ናቱ ከኢ​ያሱ ወገን የዮ​ዳኤ ልጆች ዘጠኝ መቶ ሰባ ሦስት።"
                        },
                        {
                            "verse": 37,
                            "text": "የኢ​ሜር ልጆች ሺህ አምሳ ሁለት።"
                        },
                        {
                            "verse": 38,
                            "text": "የፋ​ስ​ኮር ልጆች ሺህ ሁለት መቶ አርባ ሰባት።"
                        },
                        {
                            "verse": 39,
                            "text": "የኤ​ረም ልጆች ሺህ ዐሥራ ሰባት።"
                        },
                        {
                            "verse": 40,
                            "text": "ሌዋ​ው​ያኑ፤ ከሁ​ድያ ልጆች ወገን የኢ​ዮ​ስ​ስና የቀ​ዳ​ም​ሔል ልጆች ሰባ አራት።"
                        },
                        {
                            "verse": 41,
                            "text": "መዘ​ም​ራኑ የአ​ሳፍ ልጆች መቶ ሃያ ስም​ንት።"
                        },
                        {
                            "verse": 42,
                            "text": "የበ​ረ​ኞች ልጆች፥ የሰ​ሎም ልጆች፥ የአ​ጤር ልጆች፥ የጤ​ል​ሞን ልጆች፥ የዓ​ቁብ ልጆች፥ የሐ​ጢጣ ልጆች፥ የሰ​በ​ዋይ ልጆች ሁሉ መቶ ሠላሳ ዘጠኝ።"
                        },
                        {
                            "verse": 43,
                            "text": "ናታ​ኒም፤ የሲሓ ልጆች፥ የሐ​ሡፊ ልጆች፥ የጠ​ብ​ዖት ልጆች፤"
                        },
                        {
                            "verse": 44,
                            "text": "የቃ​ዴስ ልጆች፥ የሲ​ሔል ልጆች፥ የፋ​ዶን ልጆች፤"
                        },
                        {
                            "verse": 45,
                            "text": "የል​ባና ልጆች፥ የአ​ጋባ ልጆች፥ የዓ​ቁብ ልጆች፥"
                        },
                        {
                            "verse": 46,
                            "text": "የአ​ጋብ ልጆች፥ የሰ​ላሚ ልጆች፥ የሐ​ናን ልጆች፤"
                        },
                        {
                            "verse": 47,
                            "text": "የጋ​ዱል ልጆች፥ የጋ​ሐር ልጆች፥ የራ​እያ ልጆች፤"
                        },
                        {
                            "verse": 48,
                            "text": "የረ​አ​ሶን ልጆች፥ የኒ​ቆዳ ልጆች፥ የጋ​ሴም ልጆች፤"
                        },
                        {
                            "verse": 49,
                            "text": "የዓ​ዝ​ያት ልጆች፥ የፋ​ሒስ ልጆች፥ የባሲ ልጆች፤"
                        },
                        {
                            "verse": 50,
                            "text": "የአ​ሲና ልጆች፥ የም​ዑ​ና​ው​ያን ልጆች፥ የና​ፌ​ሶን ልጆች፤"
                        },
                        {
                            "verse": 51,
                            "text": "የበ​ቅ​ቡቅ ልጆች፥ የሐ​ቁፋ ልጆች፥ የሐ​ር​ሑር ልጆች፤"
                        },
                        {
                            "verse": 52,
                            "text": "የበ​ስ​ሎት ልጆች፥ የማ​ሁድ ልጆች፥ የአ​ሪስ ልጆች፤"
                        },
                        {
                            "verse": 53,
                            "text": "የበ​ር​ቆስ ልጆች፥ የሲ​ሣራ ልጆች፥ የቴማ ልጆች፥"
                        },
                        {
                            "verse": 54,
                            "text": "የን​ስያ ልጆች፥ የአ​ጡፋ ልጆች።"
                        },
                        {
                            "verse": 55,
                            "text": "የሰ​ሎ​ሞን አገ​ል​ጋ​ዮች ልጆች፤ የሳጢ ልጆች፥ የሰ​ፌ​ርታ ልጆች፥ የፋ​ዱ​ርሓ ልጆች፤"
                        },
                        {
                            "verse": 56,
                            "text": "የኢ​ያ​ሔል ልጆች፥ የደ​ር​ቆን ልጆች፥ የጌ​ዴል ልጆች፤"
                        },
                        {
                            "verse": 57,
                            "text": "የሰ​ፋ​ጥ​ያስ ልጆች፥ የአ​ጤል ልጆች፥ የፎ​ኬ​ርት ልጆች፥ የሐ​ፂ​ባ​ይም ልጆች፥ የአሚ ልጆች።"
                        },
                        {
                            "verse": 58,
                            "text": "እነ​ዚህ ናታ​ኒም ሁሉና የሰ​ሎ​ሞን አገ​ል​ጋ​ዮች ልጆች ሦስት መቶ ዘጠና ሁለት ነበሩ።"
                        },
                        {
                            "verse": 59,
                            "text": "ከቲ​ል​ሜላ፥ ከቴ​ላ​ርሳ፥ ከክ​ሩብ፥ ከሐ​ዳን፥ ከኤ​ሜር የወጡ እነ​ዚህ ነበሩ፤ ነገር ግን የአ​ባ​ቶ​ቻ​ቸ​ውን ቤቶ​ችና ዘራ​ቸ​ውን ወይም ከእ​ስ​ራ​ኤል ወገን መሆ​ና​ቸ​ውን ያስ​ታ​ውቁ ዘንድ አል​ቻ​ሉም፤"
                        },
                        {
                            "verse": 60,
                            "text": "የዳ​ላያ ልጆች፥"
                        },
                        {
                            "verse": 61,
                            "text": "ከካ​ህ​ና​ቱም ልጆች፤ የአ​ብያ ልጆች፥ የአ​ቆስ ልጆች፥ ከገ​ለ​ዓ​ዳ​ዊው ከቤ​ር​ዜሊ ልጆች ሚስት ያገባ፥ በስ​ማ​ቸ​ውም የተ​ጠራ የቤ​ር​ዜሊ ልጆች።"
                        },
                        {
                            "verse": 62,
                            "text": "እነ​ዚህ በት​ው​ልድ መጽ​ሐፍ ትው​ል​ዳ​ቸ​ውን ፈለጉ፤ ነገር ግን አል​ተ​ገ​ኘም፤ ከክ​ህ​ነ​ትም ተከ​ለ​ከሉ።"
                        },
                        {
                            "verse": 63,
                            "text": "ሐቲ​ር​ሰ​ስ​ታም፥ “በኡ​ሪ​ምና በቱ​ሚም የሚ​ፈ​ርድ ካህን እስ​ኪ​ነሣ ድረስ ከቅ​ዱሰ ቅዱ​ሳኑ አት​በ​ሉም” አላ​ቸው።"
                        },
                        {
                            "verse": 64,
                            "text": "ጉባ​ኤው ሁሉ አርባ ሁለት ሺህ ሦስት መቶ ስድሳ ነበሩ።"
                        },
                        {
                            "verse": 65,
                            "text": "ይኸ​ውም ሰባት ሺህ ሦስት መቶ ሠላሳ ሰባት ከነ​በሩ ከሎ​ሌ​ዎ​ቻ​ቸ​ውና ከገ​ረ​ዶ​ቻ​ቸው ሌላ ሁለት መቶ ወን​ዶች መዘ​ም​ራ​ንና ሴቶች መዘ​ም​ራ​ትም ነበ​ሩ​አ​ቸው።"
                        },
                        {
                            "verse": 66,
                            "text": "ፈረ​ሶ​ቻ​ቸ​ውም ሰባት መቶ ሠላሳ ስድ​ስት፥ በቅ​ሎ​ዎ​ቻ​ቸ​ውም ሁለት መቶ አርባ አም​ስት፥"
                        },
                        {
                            "verse": 67,
                            "text": "ግመ​ሎ​ቻ​ቸ​ውም አራት መቶ ሠላሳ አም​ስት፥ አህ​ዮ​ቻ​ቸ​ውም ስድ​ስት ሺህ ሰባት መቶ ሃያ ነበሩ።"
                        },
                        {
                            "verse": 68,
                            "text": "በኢ​የ​ሩ​ሳ​ሌ​ምም ወዳ​ለው ወደ እግ​ዚ​አ​ብ​ሔር ቤት በመጡ ጊዜ ከአ​ባ​ቶች ቤቶች አለ​ቆች አያ​ሌ​ዎች ለእ​ግ​ዚ​አ​ብ​ሔር ቤት በስ​ፍ​ራው ይሠ​ሩት ዘንድ በፈ​ቃ​ዳ​ቸው ሰጡ።"
                        },
                        {
                            "verse": 69,
                            "text": "ስድሳ አንድ ሺህም የወ​ርቅ ዳሪክ፥ አም​ስት ሺህም ምናን ብር፥ አንድ መቶም የካ​ህ​ናት ልብስ እንደ ችሎ​ታ​ቸው ወደ ሥራው ቤተ መዛ​ግ​ብት አቀ​ረቡ።"
                        },
                        {
                            "verse": 70,
                            "text": "ካህ​ና​ቱና ሌዋ​ው​ያ​ኑም፥ ከሕ​ዝ​ቡም አያ​ሌ​ዎች፥ መዘ​ም​ራ​ኑና በረ​ኞ​ቹም፥ ናታ​ኒ​ምም በከ​ተ​ሞ​ቻ​ቸው፥ እስ​ራ​ኤ​ልም ሁሉ በከ​ተ​ሞ​ቻ​ቸው ተቀ​መጡ።"
                        }
                    ]
                }
            ]
        },
        {
            "chapter": 3,
            "sections": [
                {
                    "title": "የሥ​ር​ዐተ አም​ል​ኮት እንደ ገና መጀ​መር",
                    "verses": [
                        {
                            "verse": 1,
                            "text": "ሰባ​ተ​ኛ​ውም ወር በደ​ረሰ ጊዜ፥ የእ​ስ​ራ​ኤ​ልም ልጆች በከ​ተ​ሞ​ቻ​ቸው ሳሉ፥ ሕዝቡ እንደ አንድ ሰው ሆነው ወደ ኢየ​ሩ​ሳ​ሌም ተሰ​በ​ሰቡ።"
                        },
                        {
                            "verse": 2,
                            "text": "የኢ​ዮ​ሴ​ዴ​ቅም ልጅ ኢያሱ፥ ወን​ድ​ሞ​ቹም ካህ​ናቱ፥ የሰ​ላ​ት​ያ​ልም ልጅ ዘሩ​ባ​ቤል፥ ወን​ድ​ሞ​ቹም ተነ​ሥ​ተው በእ​ግ​ዚ​አ​ብ​ሔር ሰው በሙሴ ሕግ እንደ ተጻፈ የሚ​ቃ​ጠ​ለ​ውን መሥ​ዋ​ዕት ያቀ​ር​ቡ​በት ዘንድ የእ​ስ​ራ​ኤ​ልን አም​ላክ መሠ​ዊያ ሠሩ።"
                        },
                        {
                            "verse": 3,
                            "text": "በሀ​ገ​ሩም ካሉት አሕ​ዛብ ፈር​ተው ነበ​ርና መሠ​ዊ​ያ​ውን በስ​ፍ​ራው ላይ አስ​ቀ​መ​ጡት፤ በጥ​ዋ​ትና በማ​ታም የሚ​ቃ​ጠ​ለ​ውን መሥ​ዋ​ዕት ለእ​ግ​ዚ​አ​ብ​ሔር አቀ​ረ​ቡ​በት።"
                        },
                        {
                            "verse": 4,
                            "text": "እንደ ተጻ​ፈ​ውም የዳስ በዓል አደ​ረጉ፤ እንደ ሥር​ዐ​ቱም ለየ​ዕ​ለቱ የተ​ገ​ባ​ውን የየ​ዕ​ለ​ቱን የሚ​ቃ​ጠል መሥ​ዋ​ዕት በቍ​ጥር አቀ​ረቡ።"
                        },
                        {
                            "verse": 5,
                            "text": "ከዚ​ያም በኋላ ዘወ​ትር የሚ​ቃ​ጠ​ለ​ውን መሥ​ዋ​ዕት፥ የመ​ባ​ቻ​ው​ንም መሥ​ዋ​ዕት፥ የተ​ቀ​ደ​ሱ​ት​ንም የእ​ግ​ዚ​አ​ብ​ሔር በዓ​ላት ሁሉ መሥ​ዋ​ዕት፥ ሰውም ሁሉ ለእ​ግ​ዚ​አ​ብ​ሔር በፈ​ቃድ የሰ​ጠ​ውን ቍር​ባን አቀ​ረቡ።"
                        },
                        {
                            "verse": 6,
                            "text": "በሰ​ባ​ተ​ኛ​ውም ወር በመ​ጀ​መ​ሪ​ያው ቀን ለእ​ግ​ዚ​አ​ብ​ሔር የሚ​ቃ​ጠል መሥ​ዋ​ዕት ማቅ​ረብ ጀመሩ፤ የእ​ግ​ዚ​አ​ብ​ሔር መቅ​ደስ ግን ገና አል​ተ​መ​ሠ​ረ​ተም ነበር።"
                        },
                        {
                            "verse": 7,
                            "text": "ለጠ​ራ​ቢ​ዎ​ችና ለአ​ና​ጢ​ዎ​ችም ብር"
                        },
                        {
                            "verse": 8,
                            "text": "በኢ​የ​ሩ​ሳ​ሌ​ምም ወዳ​ለው ወደ እግ​ዚ​አ​ብ​ሔር ቤት በመጡ በሁ​ለ​ተ​ኛው ዓመት በሁ​ለ​ተ​ኛ​ውም ወር የሰ​ላ​ት​ያል ልጅ ዘሩ​ባ​ቤል፥ የኢ​ዮ​ሴ​ዴ​ቅም ልጅ ኢያሱ፥ የቀ​ሩ​ትም ወን​ድ​ሞ​ቻ​ቸው ካህ​ና​ትና ሌዋ​ው​ያን፥ ከም​ርኮ ወደ ኢየ​ሩ​ሳ​ሌ​ምም የተ​መ​ለ​ሱት ሁሉ ጀመሩ፤ ሌዋ​ው​ያ​ን​ንም ከሃያ ዓመት ጀምሮ ከዚ​ያም በላይ የእ​ግ​ዚ​አ​ብ​ሔ​ርን ቤት ሥራ እን​ዲ​ያ​ሠ​ሩት ሾሙ​አ​ቸው።"
                        },
                        {
                            "verse": 9,
                            "text": "ኢያ​ሱም፥ ልጆ​ቹም ተሾሙ፤ ወን​ድ​ሞ​ቹም፥ የይ​ሁ​ዳም ልጆች ቀደ​ም​ያ​ልና ልጆቹ፥ የኢ​ን​ሐ​ዳ​ድም ልጆች፥ ልጆ​ቻ​ቸ​ውና ወን​ድ​ሞ​ቻ​ቸው ሌዋ​ው​ያ​ንም የእ​ግ​ዚ​አ​ብ​ሔ​ርን ቤት የሚ​ሠ​ሩ​ትን ያሠሩ ዘንድ በአ​ን​ድ​ነት ቆሙ።"
                        },
                        {
                            "verse": 10,
                            "text": "አና​ጢ​ዎ​ቹም የእ​ግ​ዚ​አ​ብ​ሔ​ርን መቅ​ደስ ይሠሩ ዘንድ መሠ​ረት በጣሉ ጊዜ ካህ​ናቱ ልብ​ሳ​ቸ​ውን ለብ​ሰው መለ​ከ​ቱን ይዘው፥ የአ​ሳ​ፍም ልጆች ሌዋ​ው​ያን ጸና​ጽል ይዘው እንደ እስ​ራ​ኤል ንጉሥ እንደ ዳዊት ሥር​ዐት እግ​ዚ​አ​ብ​ሔ​ርን ያመ​ሰ​ግኑ ዘንድ ቆሙ።"
                        },
                        {
                            "verse": 11,
                            "text": "ደግሞ፥ “ቸር ነውና፥ ለእ​ስ​ራ​ኤ​ልም ምሕ​ረቱ ለዘ​ለ​ዓ​ለም ነውና” እያሉ እግ​ዚ​አ​ብ​ሔ​ርን እያ​መ​ሰ​ገ​ኑና እያ​ከ​በሩ እርስ በር​ሳ​ቸው ያስ​ተ​ዛ​ዝሉ ነበር፤ የእ​ግ​ዚ​አ​ብ​ሔ​ርም ቤት በተ​መ​ሠ​ረተ ጊዜ ሕዝቡ ሁሉ እግ​ዚ​አ​ብ​ሔ​ርን እያ​ከ​በሩ በታ​ላቅ ድምፅ ዘመሩ።"
                        },
                        {
                            "verse": 12,
                            "text": "የፊ​ተ​ኛ​ውን ቤት ያዩ ሽማ​ግ​ሌ​ዎች የሆኑ ብዙ ካህ​ና​ትና ሌዋ​ው​ያን፥ የአ​ባ​ቶ​ችም ቤቶች አለ​ቆች ግን ይህ መቅ​ደስ በፊ​ታ​ቸው በተ​መ​ሠ​ረተ ጊዜ በታ​ላቅ ድምፅ ያለ​ቅሱ ነበር፤ ብዙ ሰዎ​ችም እየ​ዘ​መሩ በደ​ስታ ይጮኹ ነበር፤"
                        },
                        {
                            "verse": 13,
                            "text": "ደስ ብሎ​አ​ቸው የሚ​ጮ​ኹ​ትን ድምፅ ከሕ​ዝቡ ልቅሶ ድምፅ መለ​የት የሚ​ችል አል​ነ​በ​ረም፥ ሕዝቡ በታ​ላቅ ድምፅ ይጮኽ ነበ​ርና ድም​ፁም ከሩቅ ይሰማ ነበ​ርና።"
                        }
                    ]
                }
            ]
        },
        {
            "chapter": 4,
            "sections": [
                {
                    "title": "",
                    "verses": [
                        {
                            "verse": 1,
                            "text": "የይ​ሁ​ዳና የብ​ን​ያ​ምም ጠላ​ቶች፥ የም​ር​ኮ​ኞቹ ልጆች ለእ​ስ​ራ​ኤል አም​ላክ ለእ​ግ​ዚ​አ​ብ​ሔር መቅ​ደስ እን​ደ​ሚ​ሠሩ ሰሙ።"
                        },
                        {
                            "verse": 2,
                            "text": "ወደ ዘሩ​ባ​ቤ​ልና ወደ አባ​ቶች ቤቶች አለ​ቆ​ችም ቀር​በው፥ “የአ​ሦር ንጉሥ አስ​ራ​ዶን ወደ​ዚህ ካመ​ጣን ቀን ጀምሮ ለአ​ም​ላ​ካ​ችሁ እን​ሠ​ዋ​ለ​ንና፥ እንደ እና​ን​ተም እን​ፈ​ል​ገ​ዋ​ለ​ንና ከእ​ና​ንተ ጋር እን​ሥራ” አሉ​አ​ቸው።"
                        },
                        {
                            "verse": 3,
                            "text": "ዘሩ​ባ​ቤ​ልና ኢያ​ሱም፥ የቀ​ሩ​ትም የእ​ስ​ራ​ኤል አባ​ቶች ቤቶች አለ​ቆች፥ “የአ​ም​ላ​ካ​ች​ንን ቤት መሥ​ራት ለእ​ኛና ለእ​ና​ንተ አይ​ደ​ለም፤ እኛ ራሳ​ችን ግን የፋ​ርስ ንጉሥ ቂሮስ እን​ዳ​ዘ​ዘን ለአ​ም​ላ​ካ​ችን ለእ​ግ​ዚ​አ​ብ​ሔር ቤት እን​ሠ​ራ​ለን” አሉ​አ​ቸው።"
                        },
                        {
                            "verse": 4,
                            "text": "የሀ​ገ​ሩም ሕዝብ የይ​ሁ​ዳን ሕዝብ እጅግ ያዳ​ክሙ ነበር፤ እን​ዳ​ይ​ሠ​ሩም ከለ​ከ​ሉ​አ​ቸው፤"
                        },
                        {
                            "verse": 5,
                            "text": "ምክ​ራ​ቸ​ው​ንም ያፈ​ርሱ ዘንድ በፋ​ርሱ ንጉሥ በቂ​ሮስ ዘመን ሁሉ እስከ ፋርስ ንጉሥ እስከ ዳር​ዮስ መን​ግ​ሥት ድረስ መካ​ሪ​ዎ​ችን ገዙ​ባ​ቸው።"
                        },
                        {
                            "verse": 6,
                            "text": "በአ​ሕ​ሳ​ዊ​ሮ​ስም"
                        },
                        {
                            "verse": 7,
                            "text": "በአ​ር​ተ​ሰ​ስታ"
                        },
                        {
                            "verse": 8,
                            "text": "አዛዡ ሬሁም፥ ጸሓ​ፊ​ውም ሲም​ሳይ በኢ​የ​ሩ​ሳ​ሌም ላይ ለን​ጉሡ ለአ​ር​ተ​ሰ​ስታ አንድ የክስ ደብ​ዳቤ ጻፉ።"
                        },
                        {
                            "verse": 9,
                            "text": "አዛዡ ሬሁም፥ ጸሓ​ፊ​ውም ሲም​ሳይ፥ የቀ​ሩ​ትም ተባ​ባ​ሪ​ዎ​ቻ​ቸው፥ ዲና​ው​ያን፥ አፈ​ር​ሳ​ት​ካ​ዋ​ያን፥ ጠር​ፈ​ላ​ው​ያን፥ አፈ​ር​ሳ​ው​ያን፥ አር​ካ​ው​ያን፥ ባቢ​ሎ​ና​ው​ያን፥ ሱስ​ና​ካ​ው​ያን፥ ዴሐ​ው​ያን፥ ኤላ​ማ​ው​ያን፥"
                        },
                        {
                            "verse": 10,
                            "text": "ታላ​ቁና ኀይ​ለ​ኛው አስ​ና​ፍር ያፈ​ለ​ሳ​ቸው፥ በሰ​ማ​ር​ያና በወ​ንዝ ማዶ ያኖ​ራ​ቸው፥ የቀ​ሩ​ትም አሕ​ዛብ ደብ​ዳ​ቤ​ውን ጻፉ።"
                        },
                        {
                            "verse": 11,
                            "text": "ለን​ጉሡ ለአ​ር​ተ​ሰ​ስታ የላ​ኩት የደ​ብ​ዳቤ ቃልም ይህ ነው፥ “በወ​ንዝ ማዶ ያሉት ሰዎች ባሪ​ያ​ዎ​ችህ፤"
                        },
                        {
                            "verse": 12,
                            "text": "አሁ​ንም ከአ​ንተ ዘንድ የወጡ አይ​ሁድ ወደ እኛ ወደ ኢየ​ሩ​ሳ​ሌም እንደ መጡ ጌታ​ቸው ንጉሡ ይወቅ፤ ዐመ​ፀ​ኛ​ዪ​ቱ​ንና እጅ​ግም የከ​ፋ​ች​ቱን ከተማ ይሠ​ራሉ፤ ቅጥ​ር​ዋ​ንም ያድ​ሳሉ፤ መሠ​ረ​ቷ​ንም ጠገኑ።"
                        },
                        {
                            "verse": 13,
                            "text": "አሁ​ንም ይህች ከተማ የተ​ሠ​ራች እንደ ሆነ፥ ቅጥ​ር​ዋም የታ​ደሰ እንደ ሆነ፥ ግብ​ርና ቀረጥ መጥ​ንም"
                        },
                        {
                            "verse": 14,
                            "text": "ንጉ​ሡ​ንም ሲያ​ቃ​ል​ሉት ማየት አይ​ገ​ባ​ን​ምና ስለ​ዚህ ልከን ለን​ጉሡ አስ​ታ​ው​ቀ​ናል፤"
                        },
                        {
                            "verse": 15,
                            "text": "በአ​ባ​ቶ​ችህ ታሪክ መጽ​ሐፍ ምር​መራ ይደ​ረግ፤ በዚ​ያም በታ​ሪክ መጽ​ሐፍ ይህች ከተማ ዐመ​ፀኛ እንደ ሆነች፥ ነገ​ሥ​ታ​ት​ንና አው​ራ​ጃ​ዎ​ች​ንም እንደ ጎዳች፥ ከጥ​ን​ቱም የገ​ባ​ሮች ሽፍ​ት​ነት በእ​ር​ስዋ እንደ ተጀ​መረ ታገ​ኛ​ለህ፤ ታው​ቃ​ለ​ህም፤ ስለ​ዚ​ህም ይህች ከተማ ፈርሳ ነበር።"
                        },
                        {
                            "verse": 16,
                            "text": "ይህ​ችም ከተማ የተ​ሠ​ራች እንደ ሆነ፥ ቅጥ​ር​ዋም የታ​ደሰ እንደ ሆነ፥ ሰላም እን​ደ​ማ​ይ​ኖ​ርህ ለን​ጉሡ እና​ስ​ታ​ው​ቃ​ለን።”"
                        },
                        {
                            "verse": 17,
                            "text": "ንጉ​ሡም ለአ​ዛዡ ለሬ​ሁም፥ ለጸ​ሓ​ፊ​ውም ለሲ​ም​ሳይ፥ በሰ​ማ​ር​ያና በወ​ንዝ ማዶም ለተ​ቀ​መ​ጡ​ትና ለቀ​ሩት ተባ​ባ​ሪ​ዎ​ቻ​ቸው እን​ዲህ የሚ​ለ​ውን መልስ ላከ፥ “ሰላም ለእ​ና​ንተ ይሁን።"
                        },
                        {
                            "verse": 18,
                            "text": "አሁ​ንም ወደ እኛ የላ​ካ​ች​ሁት መል​እ​ክ​ተኛ ወደ እኔ ደረሰ"
                        },
                        {
                            "verse": 19,
                            "text": "እኔም አዝ​ዣ​ለሁ፤ ተመ​ረ​መ​ረም፤ ይህ​ችም ከተማ ከጥ​ንት ጀምራ በነ​ገ​ሥ​ታት ላይ ዐመ​ፀኛ እንደ ነበ​ረች፥ በእ​ር​ስ​ዋም ዐመ​ፅና ሽፍ​ት​ነት እንደ ተደ​ረገ ተገኘ።"
                        },
                        {
                            "verse": 20,
                            "text": "በኢ​የ​ሩ​ሳ​ሌ​ምም እጅግ ኀያ​ላን ነገ​ሥ​ታት ነበሩ፤ በወ​ን​ዝም ማዶ ያለ​ውን ሀገር ሁሉ ይገዙ ነበር፤ ግብ​ር​ንና እጅ መን​ሻ​ንም ይቀ​በሉ ነበር።"
                        },
                        {
                            "verse": 21,
                            "text": "አሁ​ንም እነ​ዚህ ሰዎች ሥራ​ውን እን​ዲ​ተዉ፥ ይህ​ችም ከተማ እን​ዳ​ት​ሠራ ትእ​ዛዝ ስጡ።"
                        },
                        {
                            "verse": 22,
                            "text": "በዚ​ህም ነገር እን​ዳ​ት​ሳ​ሳቱ፥ በነ​ገ​ሥ​ታ​ቱም ጕዳ​ትና ጥፋት እን​ዳ​ይ​በዛ ተጠ​ን​ቀቁ።”"
                        },
                        {
                            "verse": 23,
                            "text": "የን​ጉ​ሡም የአ​ር​ተ​ሰ​ስታ መል​እ​ክ​ተኛ በደ​ረሰ ጊዜ በአ​ዛዡ በሬ​ሁ​ምና በጸ​ሓ​ፊው በሲ​ም​ሳይ፥ በተ​ባ​ባ​ሪ​ዎ​ቻ​ቸ​ውም ፊት መል​እ​ክ​ቱን ባነ​በበ ጊዜ ፈጥ​ነው ወደ ኢየ​ሩ​ሳ​ሌም ወደ አይ​ሁድ"
                        },
                        {
                            "verse": 24,
                            "text": "በዚ​ያን ጊዜም በኢ​የ​ሩ​ሳ​ሌም ያለው የእ​ግ​ዚ​አ​ብ​ሔር ቤት ሥራ ተቋ​ረጠ፤ እስከ ፋር​ስም ንጉሥ እስከ ዳር​ዮስ መን​ግ​ሥት እስከ ሁለ​ተ​ኛው ዓመት ድረስ ተጓ​ጐለ።"
                        }
                    ]
                }
            ]
        },
        {
            "chapter": 5,
            "sections": [
                {
                    "title": "የቤተ መቅ​ደሱ ሥራ እንደ ገና መቀ​ጠሉ",
                    "verses": [
                        {
                            "verse": 1,
                            "text": "ነቢ​ያቱ ሐጌና የአዶ ልጅ ዘካ​ር​ያስ በይ​ሁ​ዳና በኢ​የ​ሩ​ሳ​ሌም ለነ​በሩ አይ​ሁድ በእ​ስ​ራ​ኤል አም​ላክ ስም ትን​ቢት ተና​ገ​ሩ​ላ​ቸው።"
                        },
                        {
                            "verse": 2,
                            "text": "በዚ​ያን ጊዜም የሰ​ላ​ት​ያል ልጅ ዘሩ​ባ​ቤል የኢ​ዮ​ሴ​ዴ​ቅም ልጅ ኢያሱ ተነ​ሥ​ተው በኢ​የ​ሩ​ሳ​ሌም ያለ​ውን የእ​ግ​ዚ​አ​ብ​ሔ​ርን ቤት መሥ​ራት ጀመሩ፤ የሚ​ያ​ግ​ዙ​አ​ቸ​ውም የእ​ግ​ዚ​አ​ብ​ሔር ነቢ​ያት ከእ​ነ​ርሱ ጋር ነበሩ።"
                        },
                        {
                            "verse": 3,
                            "text": "በዚ​ያም ጊዜ በወ​ንዝ ማዶ የነ​በ​ረው ገዥ ተን​ት​ናይ፥ ደግሞ አስ​ተ​ር​ቡ​ዝ​ናይ ተባ​ባ​ሪ​ዎ​ቻ​ቸ​ውም ወደ እነ​ርሱ መጥ​ተው፥ “ይህን ቤት ትሠሩ ዘንድ ማን አዘ​ዛ​ችሁ? የም​ት​ሠ​ሩ​በ​ት​ንስ ሥል​ጣን ማን ሰጣ​ችሁ?” አሉ​አ​ቸው።"
                        },
                        {
                            "verse": 4,
                            "text": "ደግ​ሞም፥ “ይህ​ችን ከተ​ማስ የሚ​ሠሩ ሰዎች ስም ማን ማን ነው?” ብለው ጠየ​ቁ​አ​ቸው።"
                        },
                        {
                            "verse": 5,
                            "text": "የእ​ግ​ዚ​አ​ብ​ሔር ዐይን ግን በይ​ሁዳ ምር​ኮ​ኞች"
                        },
                        {
                            "verse": 6,
                            "text": "በወ​ንዙ ማዶ የነ​በ​ረው ገዥ ተን​ት​ናይ፥ ደግሞ አስ​ተ​ር​ቡ​ዝ​ናይ፥ ተባ​ባ​ሪ​ዎ​ቻ​ቸ​ውም፥ በወ​ንዙ ማዶ የነ​በ​ሩት አፈ​ር​ስ​ካ​ው​ያ​ንም ወደ ንጉሡ ወደ ዳር​ዮስ የላ​ኩት የደ​ብ​ዳ​ቤው ቃል ይህ ነበረ።"
                        },
                        {
                            "verse": 7,
                            "text": "እን​ዲ​ህም የሚል ደብ​ዳቤ ላኩ​ለት፥ “ለን​ጉሡ ለዳ​ር​ዮስ ሙሉ ሰላም ይሁን፤"
                        },
                        {
                            "verse": 8,
                            "text": "ወደ ይሁዳ ሀገር ወደ ታላ​ቁም አም​ላክ ቤት እንደ ሄድን ንጉሡ ይወቅ፤ እር​ሱም በጥሩ ድን​ጋይ ይሠ​ራል፤ በቅ​ጥ​ሩም ውስጥ ልዩ እን​ጨት ይደ​ረ​ጋል፤ ያም ሥራ በት​ጋት ይሠ​ራል፤ በእ​ጃ​ቸ​ውም ይከ​ና​ወ​ናል።"
                        },
                        {
                            "verse": 9,
                            "text": "እነ​ዚ​ያ​ንም ሽማ​ግ​ሌ​ዎች፦ ‘ይህን ቤት ትሠሩ ዘንድ ማን አዘ​ዛ​ችሁ? የም​ት​ሠ​ሩ​በ​ት​ንስ ሥል​ጣን ማን ሰጣ​ችሁ?’ ብለን ጠየ​ቅ​ና​ቸው።"
                        },
                        {
                            "verse": 10,
                            "text": "ደግ​ሞም እና​ስ​ታ​ው​ቅህ ዘንድ፥ በእ​ነ​ር​ሱም ያሉ​ትን ሹሞች ስም እን​ጽ​ፍ​ልህ ዘንድ ስማ​ቸ​ውን ጠየ​ቅን።"
                        },
                        {
                            "verse": 11,
                            "text": "እን​ደ​ዚ​ህም ብለው መለ​ሱ​ልን፦ እኛ የሰ​ማ​ይና የም​ድር አም​ላክ ባሪ​ያ​ዎች ነን፥ ከብ​ዙም ዘመን ጀምሮ ተሠ​ርቶ የነ​በ​ረ​ውን፥ ታላ​ቁም የእ​ስ​ራ​ኤል ንጉሥ ሠርቶ ፈጽ​ሞ​ላ​ቸው የነ​በ​ረ​ውን ቤት እን​ሠ​ራ​ለን።"
                        },
                        {
                            "verse": 12,
                            "text": "አባ​ቶ​ቻ​ች​ንም የሰ​ማ​ይን አም​ላክ ከአ​ስ​ቈጡ በኋላ በከ​ለ​ዳ​ዊው በባ​ቢ​ሎን ንጉሥ በና​ቡ​ከ​ደ​ነ​ፆር እጅ አሳ​ልፎ ሰጣ​ቸው፤ እር​ሱም ይህን ቤት አፈ​ረሰ፤ ሕዝ​ቡ​ንም ወደ ባቢ​ሎን አፈ​ለሰ።"
                        },
                        {
                            "verse": 13,
                            "text": "ነገር ግን በባ​ቢ​ሎን ንጉሥ በቂ​ሮስ በመ​ጀ​መ​ሪ​ያው ዓመት ንጉሡ ቂሮስ ይህን የእ​ግ​ዚ​አ​ብ​ሔ​ርን ቤት ይሠሩ ዘንድ አዘዘ።"
                        },
                        {
                            "verse": 14,
                            "text": "ናቡ​ከ​ደ​ነ​ፆ​ርም በኢ​የ​ሩ​ሳ​ሌም ከነ​በ​ረው መቅ​ደስ የወ​ሰ​ደ​ውን፥ ወደ ባቢ​ሎ​ንም መቅ​ደስ ያፈ​ለ​ሰ​ውን የእ​ግ​ዚ​አ​ብ​ሔ​ርን ቤት የወ​ር​ቁ​ንና የብ​ሩን ዕቃ ንጉሡ ቂሮስ ከባ​ቢ​ሎን መቅ​ደስ አው​ጥቶ ለቤተ መዛ​ግ​ብቱ ሹም ለሲ​ሳ​ብ​ሳር ሰጠ​ውና፦"
                        },
                        {
                            "verse": 15,
                            "text": "‘ይህን ዕቃ ይዘህ ሂድ፤ በኢ​የ​ሩ​ሳ​ሌ​ምም ባለው መቅ​ደስ በቦ​ታው አኑ​ረው፤ የእ​ግ​ዚ​አ​ብ​ሔ​ርም ቤት በስ​ፍ​ራው ይሠራ’ አለው።"
                        },
                        {
                            "verse": 16,
                            "text": "በዚያ ጊዜም ይህ ሲሳ​ብ​ሳር መጣ፤ በኢ​የ​ሩ​ሳ​ሌ​ምም ያለ​ውን የእ​ግ​ዚ​አ​ብ​ሔ​ርን ቤት መሠ​ረተ፤ ከዚ​ያም ጊዜ ጀምሮ እስከ ዛሬ ድረስ እየ​ተ​ሠራ አል​ተ​ጨ​ረ​ሰም።"
                        },
                        {
                            "verse": 17,
                            "text": "አሁ​ንም ይህ ነገር በን​ጉሡ ዐይን መል​ካም ቢሆን ይህ የእ​ግ​ዚ​አ​ብ​ሔር ቤት በኢ​የ​ሩ​ሳ​ሌም ይሠራ ዘንድ ከን​ጉሡ ከቂ​ሮስ ታዝዞ እንደ ሆነ በባ​ቢ​ሎን ባለው በን​ጉሡ ቤተ መዛ​ግ​ብት ይመ​ር​መር፤ ስለ​ዚ​ህም ነገር ንጉሡ ፈቃ​ዱን ይላ​ክ​ልን።”"
                        }
                    ]
                }
            ]
        },
        {
            "chapter": 6,
            "sections": [
                {
                    "title": "የቂ​ሮስ ትእ​ዛዝ መገ​ኘት",
                    "verses": [
                        {
                            "verse": 1,
                            "text": "በዚያ ጊዜም ንጉሡ ዳር​ዮስ በባ​ቢ​ሎን ቤተ መዛ​ግ​ብት ያሉ የታ​ሪክ መጻ​ሕ​ፍት እን​ዲ​መ​ረ​መሩ አዘዘ።"
                        },
                        {
                            "verse": 2,
                            "text": "በሜ​ዶን አው​ራጃ ባለው ባሪ"
                        },
                        {
                            "verse": 3,
                            "text": "በን​ጉሡ በቂ​ሮስ በመ​ጀ​መ​ሪ​ያው ዓመት ንጉሡ ቂሮስ በኢ​የ​ሩ​ሳ​ሌም ስላ​ለው የእ​ግ​ዚ​አ​ብ​ሔር ቤተ መቅ​ደስ እን​ዲህ ብሎ አዘዘ፥ “ይህ ቤት ይሠራ መሥ​ዋ​ዕት የሚ​ቀ​ር​ብ​በ​ትም ቦታ ይሠራ፤"
                        },
                        {
                            "verse": 4,
                            "text": "በሦ​ስት ተራ ታላ​ላቅ ድን​ጋይ፥ በአ​ንድ ተራ እን​ጨት ይደ​ረግ፤ ወጭ​ውም ከን​ጉሡ ቤት ይሰጥ።"
                        },
                        {
                            "verse": 5,
                            "text": "ናቡ​ከ​ደ​ነ​ዖ​ርም በኢ​የ​ሩ​ሳ​ሌም ካለው መቅ​ደስ ወስዶ ወደ ባቢ​ሎን ያመ​ጣው የእ​ግ​ዚ​አ​ብ​ሔር ቤት የወ​ር​ቅና የብር ዕቃ ይሰጥ፤ በኢ​የ​ሩ​ሳ​ሌ​ምም ወዳ​ለው መቅ​ደስ ወደ ስፍ​ራው ይወ​ሰድ፤ በእ​ግ​ዚ​አ​ብ​ሔ​ርም ቤት ይኑር።"
                        },
                        {
                            "verse": 6,
                            "text": "“አሁ​ንም አንተ በወ​ንዝ ማዶ ያለ​ኸው የሀ​ገሩ ገዥ ተን​ት​ናይ ደግሞ አሰ​ተ​ር​ቡ​ዝ​ናይ በወ​ንዝ ማዶም ያሉ ተባ​ባ​ሪ​ዎ​ቻ​ችሁ አፈ​ር​ስ​ካ​ው​ያን ከዚያ ራቁ፤"
                        },
                        {
                            "verse": 7,
                            "text": "ይህም የእ​ግ​ዚ​አ​ብ​ሔር ቤት ይሠራ ዘንድ ተዉ፤ የአ​ይ​ሁ​ድም አለ​ቆ​ችና የአ​ይ​ሁድ ሽማ​ግ​ሌ​ዎች ይህን የእ​ግ​ዚ​አ​ብ​ሔ​ርን ቤት በስ​ፍ​ራው ይሥሩ።"
                        },
                        {
                            "verse": 8,
                            "text": "ይህን የእ​ግ​ዚ​አ​ብ​ሔ​ርን ቤት ይሠሩ ዘንድ ለአ​ይ​ሁድ ሽማ​ግ​ሌ​ዎች የም​ታ​ደ​ር​ጉ​ትን፥ በወ​ንዝ ማዶ ካለው ሀገር ከሚ​መ​ጣው ግብር ከን​ጉሡ ገን​ዘብ ለእ​ነ​ዚህ ሰዎች ወጭ​ውን በት​ጋት እን​ድ​ት​ሰ​ጡ​አ​ቸው፥ ሥራም እን​ዳ​ታ​ስ​ፈ​ቱ​አ​ቸው አዝ​ዣ​ለሁ።"
                        },
                        {
                            "verse": 9,
                            "text": "ለሰ​ማይ አም​ላክ ለሚ​ቃ​ጠል መሥ​ዋ​ዕት የሚ​ያ​ስ​ፈ​ል​ገ​ውን ወይ​ፈ​ኖ​ችና አውራ በጎች፥ ጠቦ​ቶ​ችም፥ በኢ​የ​ሩ​ሳ​ሌ​ምም እን​ዳሉ እንደ ካህ​ናቱ ቃል ስን​ዴና ጨው፥ የወ​ይን ጠጅና ዘይት የሚ​ጠ​ይ​ቋ​ች​ሁን ዕለት ዕለት ስጡ​አ​ቸው።"
                        },
                        {
                            "verse": 10,
                            "text": "ይኸ​ውም ለሰ​ማይ አም​ላክ በጎ መዓዛ የሆ​ነ​ውን መሥ​ዋ​ዕት ያቀ​ርቡ ዘንድ፥ ለን​ጉ​ሡና ለል​ጆ​ቹም ዕድሜ ይጸ​ልዩ ዘንድ ነው።"
                        },
                        {
                            "verse": 11,
                            "text": "ይህ​ንም ትእ​ዛዝ የሚ​ለ​ውጥ ሁሉ ምሰ​ሶው ከቤቱ ተነ​ቅሎ እርሱ ይሰ​ቀ​ል​በት፤ በላ​ዩም ይገ​ደል፤ ቤቱም የጕ​ድፍ መጣያ ይደ​ረግ ብዬ አዝ​ዣ​ለሁ።"
                        },
                        {
                            "verse": 12,
                            "text": "ስሙ በዚያ የሚ​ኖር አም​ላክ ይህን ይለ​ውጡ ዘንድ፥ በኢ​የ​ሩ​ሳ​ሌም ያለ​ው​ንም የእ​ግ​ዚ​አ​ብ​ሔ​ርን ቤት ያፈ​ር​ሱት ዘንድ እጃ​ቸ​ውን የሚ​ዘ​ረ​ጉ​ትን ነገ​ሥ​ታ​ትና አሕ​ዛብ ሁሉ ያጥፋ። እኔ ዳር​ዮስ ይህን አዝ​ዣ​ለሁ፤ በት​ጋት ይፈ​ጸም።”"
                        },
                        {
                            "verse": 13,
                            "text": "ንጉ​ሡም ዳር​ዮስ እንደ ላከው ቃል፥ በዚ​ያን ጊዜ በወ​ንዝ ማዶ ያለ ገዥ ተን​ት​ናይ ደግሞ አስ​ተ​ር​ቡ​ዝ​ናይ ተባ​ባ​ሪ​ዎ​ቻ​ቸ​ውም እን​ዲሁ ተግ​ተው አደ​ረጉ።"
                        },
                        {
                            "verse": 14,
                            "text": "የአ​ይ​ሁድ ሽማ​ግ​ሌ​ዎ​ችና ሌዋ​ው​ያ​ንም በነ​ቢዩ በሐ​ጌና በአዶ ልጅ በዘ​ካ​ር​ያስ ትን​ቢት መሠ​ረት ሠሩ፤ ተከ​ና​ወ​ነ​ላ​ቸ​ውም። እንደ እስ​ራ​ኤ​ልም አም​ላክ ትእ​ዛዝ፥ እንደ ፋር​ስም ነገ​ሥ​ታት እንደ ቂሮ​ስና እንደ ዳር​ዮስ፥ እንደ አር​ተ​ሰ​ስ​ታም"
                        },
                        {
                            "verse": 15,
                            "text": "ይህም ቤት በን​ጉሡ በዳ​ር​ዮስ መን​ግ​ሥት በስ​ድ​ስ​ተ​ኛው ዓመት አዳር በሚ​ባል ወር በሦ​ስ​ተ​ኛው ቀን ተፈ​ጸመ።"
                        },
                        {
                            "verse": 16,
                            "text": "የእ​ስ​ራ​ኤ​ልም ልጆች ካህ​ና​ቱና ሌዋ​ው​ያኑ፥ የቀ​ሩ​ትም የም​ር​ኮ​ኞች ልጆች የዚ​ህን የእ​ግ​ዚ​አ​ብ​ሔ​ርን ቤት ቅዳሴ በደ​ስታ አደ​ረጉ።"
                        },
                        {
                            "verse": 17,
                            "text": "በዚ​ህም በእ​ግ​ዚ​አ​ብ​ሔር ቤት ቅዳሴ መቶ ወይ​ፈ​ኖ​ችና ሁለት መቶ አውራ በጎች፥ አራት መቶም የበግ ጠቦ​ቶች አቀ​ረቡ፤ ስለ ኀጢ​አ​ትም መሥ​ዋ​ዕት እንደ እስ​ራ​ኤል ነገ​ዶች ቍጥር ለእ​ስ​ራ​ኤል ሁሉ ዐሥራ ሁለት አውራ ፍየ​ሎች አቀ​ረቡ።"
                        },
                        {
                            "verse": 18,
                            "text": "በሙ​ሴም መጽ​ሐፍ እንደ ተጻ​ፈው በኢ​የ​ሩ​ሳ​ሌም ባለው በእ​ግ​ዚ​አ​ብ​ሔር አገ​ል​ግ​ሎት ላይ ካህ​ና​ቱን በየ​ማ​ዕ​ር​ጋ​ቸው፥ ሌዋ​ው​ያ​ኑ​ንም በየ​ክ​ፍ​ላ​ቸው አቆሙ።"
                        },
                        {
                            "verse": 19,
                            "text": "የም​ር​ኮ​ኞ​ቹም ልጆች በመ​ጀ​መ​ሪ​ያው ወር በዐ​ሥራ አራ​ተ​ኛው ቀን ፋሲ​ካ​ውን አደ​ረጉ።"
                        },
                        {
                            "verse": 20,
                            "text": "ካህ​ና​ቱና ሌዋ​ው​ያ​ኑም አንድ ሆነው ነጽ​ተው ነበር፤ ሁሉም ንጹ​ሓን ነበሩ፤ ለም​ር​ኮ​ኞ​ቹም ልጆች ሁሉ፥ ለወ​ን​ድ​ሞ​ቻ​ቸው ለካ​ህ​ናቱ፥ ለራ​ሳ​ቸ​ውም የፋ​ሲ​ካ​ውን በግ ዐረዱ።"
                        },
                        {
                            "verse": 21,
                            "text": "ከም​ር​ኮም ተመ​ል​ሰው የመ​ጡት የእ​ስ​ራ​ኤል ልጆች፥ የእ​ስ​ራ​ኤ​ልን አም​ላክ እግ​ዚ​አ​ብ​ሔ​ርን ይፈ​ልጉ ዘንድ ራሳ​ቸ​ውን ከም​ድር አሕ​ዛብ ርኵ​ሰት ለይ​ተው ወደ እነ​ርሱ መጥ​ተው የነ​በ​ሩት ሁሉ ፋሲ​ካ​ውን በሉ፤"
                        },
                        {
                            "verse": 22,
                            "text": "እግ​ዚ​አ​ብ​ሔ​ርም ደስ አሰ​ኝ​ቶ​አ​ቸ​ዋ​ልና፥ የእ​ስ​ራ​ኤ​ል​ንም አም​ላክ የእ​ግ​ዚ​አ​ብ​ሔ​ርን ቤት ለመ​ሥ​ራት እጃ​ቸ​ውን ያጸና ዘንድ የአ​ሦ​ርን ንጉሥ ልብ ወደ እነ​ርሱ መል​ሶ​አ​ልና የቂ​ጣ​ውን በዓል ሰባት ቀን በደ​ስታ አደ​ረጉ።"
                        }
                    ]
                }
            ]
        },
        {
            "chapter": 7,
            "sections": [
                {
                    "title": "የዕ​ዝራ ወደ ኢየ​ሩ​ሳ​ሌም መው​ጣት",
                    "verses": [
                        {
                            "verse": 1,
                            "text": "ከዚ​ህም ነገር በኋላ በፋ​ርስ ንጉሥ በአ​ር​ተ​ሰ​ስታ"
                        },
                        {
                            "verse": 2,
                            "text": "የሰ​ሎም ልጅ፥ የሳ​ዶቅ ልጅ፥ የአ​ኪ​ጦብ ልጅ፥"
                        },
                        {
                            "verse": 3,
                            "text": "የአ​ማ​ርያ"
                        },
                        {
                            "verse": 4,
                            "text": "የዘ​ራ​እያ ልጅ፥ የኡዚ ልጅ፥ የቡቂ ልጅ፥"
                        },
                        {
                            "verse": 5,
                            "text": "የአ​ቢሱ ልጅ፥ የፊ​ን​ሐስ ልጅ፥ የአ​ል​ዓ​ዛር ልጅ፥ የመ​ጀ​መ​ሪ​ያው ካህን የአ​ሮን ልጅ፥"
                        },
                        {
                            "verse": 6,
                            "text": "ይህም ዕዝራ ከባ​ቢ​ሎን ወጣ፤ እር​ሱም የእ​ስ​ራ​ኤል አም​ላክ እግ​ዚ​አ​ብ​ሔር ለሙሴ የሰ​ጠ​ውን ሕግ ዐዋቂ ነበረ፤ የአ​ም​ላ​ኩም የእ​ግ​ዚ​አ​ብ​ሔር እጅ በእ​ርሱ ላይ ነበ​ረ​ችና ንጉሡ ያሻ​ውን ሁሉ ሰጠው።"
                        },
                        {
                            "verse": 7,
                            "text": "ከእ​ስ​ራ​ኤ​ልም ልጆች ከካ​ህ​ና​ቱም፥ ከሌ​ዋ​ው​ያ​ኑም፥ ከመ​ዘ​ም​ራ​ኑም፥ ከበ​ረ​ኞ​ቹም፥ ከና​ታ​ኒ​ምም በን​ጉሡ በአ​ር​ተ​ሰ​ስታ በሰ​ባ​ተ​ኛው ዓመት ዐያ​ሌ​ዎች ወደ ኢየ​ሩ​ሳ​ሌም ወጡ።"
                        },
                        {
                            "verse": 8,
                            "text": "በን​ጉ​ሡም በሰ​ባ​ተ​ኛው ዓመት በአ​ም​ስ​ተ​ኛው ወር ወደ ኢየ​ሩ​ሳ​ሌም ደረሱ።"
                        },
                        {
                            "verse": 9,
                            "text": "በመ​ጀ​መ​ሪ​ያ​ውም ወር በአ​ን​ደ​ኛው ቀን ከባ​ቢ​ሎን ሊወጡ ጀመሩ፤ መል​ካ​ሚ​ቱም የአ​ም​ላኩ እጅ በእ​ርሱ ላይ ነበ​ረ​ችና በአ​ም​ስ​ተ​ኛው ወር በመ​ጀ​መ​ሪ​ያው ቀን ወደ ኢየ​ሩ​ሳ​ሌም ደረሱ።"
                        },
                        {
                            "verse": 10,
                            "text": "ዕዝ​ራም የእ​ግ​ዚ​አ​ብ​ሔ​ርን ሕግ ይፈ​ል​ግና ያደ​ርግ ዘንድ፥ ለእ​ስ​ራ​ኤ​ልም ሥር​ዐ​ት​ንና ፍር​ድን ያስ​ተ​ምር ዘንድ ልቡን አዘ​ጋ​ጅቶ ነበር።"
                        },
                        {
                            "verse": 11,
                            "text": "ንጉ​ሡም አር​ተ​ሰ​ስታ"
                        },
                        {
                            "verse": 12,
                            "text": "“ከን​ጉሠ ነገ​ሥት ከአ​ር​ተ​ሰ​ስታ ለሰ​ማይ አም​ላክ ሕግ ጸሓፊ ለካ​ህኑ ለዕ​ዝራ፥ ሰላም ይሁን፤"
                        },
                        {
                            "verse": 13,
                            "text": "በመ​ን​ግ​ሥ​ቴም ውስጥ ካሉ ከእ​ስ​ራ​ኤል ሕዝብ ከካ​ህ​ና​ቱና ከሌ​ዋ​ው​ያኑ ወደ ኢየ​ሩ​ሳ​ሌም ይሄድ ዘንድ የሚ​ወ​ድድ ሁሉ ከአ​ንተ ጋር እን​ዲ​ሄድ አዝ​ዣ​ለሁ።"
                        },
                        {
                            "verse": 14,
                            "text": "ንጉ​ሡና ሰባቱ አማ​ካ​ሪ​ዎቹ በእ​ጅህ እን​ዳ​ለ​ችው እንደ አም​ላ​ክህ ሕግ ይሁ​ዳ​ንና ኢየ​ሩ​ሳ​ሌ​ምን ትጐ​በኝ ዘንድ አዝ​ዘ​ዋል፤"
                        },
                        {
                            "verse": 15,
                            "text": "ንጉ​ሡና አማ​ካ​ሪ​ዎ​ቹም መኖ​ሪ​ያው በኢ​የ​ሩ​ሳ​ሌም ለሆ​ነው ለእ​ስ​ራ​ኤል አም​ላክ በፈ​ቃ​ዳ​ቸው ያቀ​ረ​ቡ​ትን ብርና ወርቅ፥"
                        },
                        {
                            "verse": 16,
                            "text": "በባ​ቢ​ሎ​ንም አው​ራጃ ሁሉ የም​ታ​ገ​ኘ​ውን ብርና ወርቅ ሁሉ፥ ሕዝ​ቡና ካህ​ና​ቱም በኢ​የ​ሩ​ሳ​ሌም ላለው ለአ​ም​ላ​ካ​ቸው ቤት በፈ​ቃ​ዳ​ቸው የሚ​ያ​ቀ​ር​ቡ​ትን ትወ​ስድ ዘንድ አዝ​ዘ​ዋል፤"
                        },
                        {
                            "verse": 17,
                            "text": "ስለ​ዚህ በዚህ መጽ​ሐፍ ያዘ​ዝ​ሁህ ትእ​ዛዝ ይህ ነው። በዚህ ገን​ዘብ ወይ​ፈ​ኖ​ች​ንና አውራ በጎ​ችን፥ ጠቦ​ቶ​ች​ንም፥ የእ​ህ​ላ​ቸ​ው​ንና የመ​ጠ​ጣ​ቸ​ውን ቍር​ባን ተግ​ተህ ግዛ፤ በኢ​የ​ሩ​ሳ​ሌ​ምም ባለው በአ​ም​ላ​ካ​ችሁ ቤት መሠ​ዊያ ላይ አቅ​ር​ባ​ቸው።"
                        },
                        {
                            "verse": 18,
                            "text": "ከቀ​ረ​ውም ብርና ወርቅ አን​ተና ወን​ድ​ሞ​ችህ ለማ​ድ​ረግ ደስ የሚ​ያ​ሰ​ኛ​ች​ሁን ነገር እንደ አም​ላ​ካ​ችሁ ፈቃድ አድ​ርጉ።"
                        },
                        {
                            "verse": 19,
                            "text": "ስለ አም​ላ​ክ​ህም ቤት አገ​ል​ግ​ሎት የተ​ሰ​ጠ​ህን ዕቃ በኢ​የ​ሩ​ሳ​ሌም አም​ላክ ፊት አሳ​ል​ፈህ ስጥ።"
                        },
                        {
                            "verse": 20,
                            "text": "ከዚ​ህም በላይ ለማ​ው​ጣት የሚ​ያ​ስ​ፈ​ል​ግ​ህን ለአ​ም​ላ​ክህ ቤት የሚ​ያ​ሻ​ውን ነገር ከን​ጉሡ ቤተ መዛ​ግ​ብት ስጥ።"
                        },
                        {
                            "verse": 21,
                            "text": "እኔም ንጉሡ አር​ተ​ሰ​ስታ በወ​ንዝ ማዶ ላሉት ግምጃ ቤቶች ሁሉ ይህን ትእ​ዛዝ ሰጥ​ቻ​ለሁ፦ የሰ​ማይ አም​ላክ ሕግ ጸሓፊ ካህኑ ዕዝራ ከእ​ና​ንተ የሚ​ፈ​ል​ገ​ውን ሁሉ አዘ​ጋ​ጁ​ለት፤"
                        },
                        {
                            "verse": 22,
                            "text": "እስከ መቶ መክ​ሊት ብርም ቢሆን፥ እስከ መቶም የቆ​ሮስ መስ​ፈ​ሪያ ስንዴ፥ እስከ መቶም የባ​ዶስ መስ​ፈ​ሪያ የወ​ይን ጠጅ፥ እስከ መቶም የባ​ዶስ መስ​ፈ​ሪያ ዘይት ቢሆን፥ ጨውም ያለ ልክ ቢሆን፤"
                        },
                        {
                            "verse": 23,
                            "text": "በን​ጉሡ መን​ግ​ሥ​ትና በል​ጆቹ ላይ ቍጣ እን​ዳ​ይ​ሆን፥ የሰ​ማይ አም​ላክ ያዘ​ዘው ሁሉ ይደ​ረግ፤ ለሰ​ማይ አም​ላክ ቤት የታ​ዘ​ዘ​ው​ንም እን​ዳ​ታ​ቋ​ርጡ ተጠ​ን​ቀቁ።"
                        },
                        {
                            "verse": 24,
                            "text": "ደግ​ሞም በካ​ህ​ና​ቱና በሌ​ዋ​ው​ያኑ፥ በመ​ዘ​ም​ራ​ኑም፥ በበ​ረ​ኞ​ቹም፥ በና​ታ​ኒ​ምም በዚ​ህም በእ​ግ​ዚ​አ​ብ​ሔር ቤት በሚ​ሠሩ አገ​ል​ጋ​ዮች ላይ ግብ​ርና ቀረጥ እን​ዳ​ይ​ጣል፥ የም​ት​ገ​ዙ​አ​ቸ​ውም አገ​ዛዝ እን​ዳ​ይ​ኖር ብለን እና​ስ​ታ​ው​ቃ​ች​ኋ​ለን።"
                        },
                        {
                            "verse": 25,
                            "text": "አን​ተም ዕዝራ፥ በእ​ጅህ እን​ዳ​ለው እንደ አም​ላ​ክህ ጥበብ መጠን በወ​ንዝ ማዶ ባሉ ሕዝብ ሁሉ፥ የአ​ም​ላ​ክ​ህን ሕግ በሚ​ያ​ውቁ ሁሉ ላይ ይፈ​ርዱ ዘንድ ጻፎ​ች​ንና ፈራ​ጆ​ችን ሹም፤ የማ​ያ​ው​ቁ​ት​ንም አስ​ተ​ም​ሩ​አ​ቸው።"
                        },
                        {
                            "verse": 26,
                            "text": "የአ​ም​ላ​ክ​ህ​ንም ሕግ፥ የን​ጉ​ሡ​ንም ሕግ በማ​ያ​ደ​ርግ ሁሉ ላይ ሞት፥ ወይም ስደት፥ ወይም ገን​ዘብ መወ​ረስ፥ ወይም ግዞት በፍ​ጥ​ነት ይፈ​ረ​ድ​በት።”"
                        },
                        {
                            "verse": 27,
                            "text": "ያባ​ቶ​ቻ​ችን አም​ላክ እግ​ዚ​አ​ብ​ሔር ይመ​ስ​ገን፤ በኢ​የ​ሩ​ሳ​ሌም ያለ​ውን የእ​ግ​ዚ​አ​ብ​ሔ​ርን ቤት ያከ​ብር ዘንድ ይህን ነገር በን​ጉሡ ልብ ያኖረ፥"
                        },
                        {
                            "verse": 28,
                            "text": "በን​ጉሡ ፊት በሚ​መ​ክ​ሩ​ትም፥ በኀ​ያ​ላ​ኑም፥ በን​ጉሡ አለ​ቆች ሁሉ ፊት በእኔ ላይ ምሕ​ረ​ቱን ላከ። እኔም በእኔ ላይ ባለ​ችው በአ​ም​ላኬ በእ​ግ​ዚ​አ​ብ​ሔር እጅ በረ​ታሁ፤ ከእ​ኔም ጋራ ይወጡ ዘንድ ከእ​ስ​ራ​ኤል አለ​ቆ​ቹን ሰበ​ሰ​ብሁ።"
                        }
                    ]
                }
            ]
        },
        {
            "chapter": 8,
            "sections": [
                {
                    "title": "",
                    "verses": [
                        {
                            "verse": 1,
                            "text": "በን​ጉሡ በአ​ር​ተ​ሰ​ስታ"
                        },
                        {
                            "verse": 2,
                            "text": "ከፊ​ን​ሐስ ልጆች ጌር​ሶም፥ ከኢ​ታ​ምር ልጆች ዳን​ኤል፥ ከዳ​ዊት ልጆች ሐጡስ፥"
                        },
                        {
                            "verse": 3,
                            "text": "ከሴ​ኬ​ንያ ልጆች፥ ከፋ​ሮስ ልጆች ዘካ​ር​ያስ፥ ከእ​ር​ሱም ጋር የተ​ቈ​ጠሩ መቶ አምሳ ወን​ዶች ናቸው።"
                        },
                        {
                            "verse": 4,
                            "text": "ከፋ​ሐት ሞዓብ ልጆች የዘ​ር​ህያ ልጅ ኤሊ​ሆ​ዔ​ናይ፥ ከእ​ር​ሱም ጋር ሁለት መቶ ወን​ዶች።"
                        },
                        {
                            "verse": 5,
                            "text": "ከዘ​ቱ​ኤስ ልጆች የአ​ዚ​ኤል ልጅ ሴኬ​ንያ፥ ከእ​ር​ሱም ጋር ሦስት መቶ ወን​ዶች።"
                        },
                        {
                            "verse": 6,
                            "text": "ከዓ​ዴን ልጆች የዮ​ና​ታን ልጅ ዔቤድ፥ ከእ​ር​ሱም ጋራ አምሳ ወን​ዶች።"
                        },
                        {
                            "verse": 7,
                            "text": "ከኤ​ሌም ልጆች የጎ​ቶ​ልያ ልጅ የሻያ፥ ከእ​ር​ሱም ጋር ሰባ ወን​ዶች።"
                        },
                        {
                            "verse": 8,
                            "text": "ከሰ​ፋ​ጥ​ያስ ልጆች የሚ​ካ​ኤል ልጅ ዘብ​ድያ፥ ከእ​ር​ሱም ጋር ሰማ​ንያ ወን​ዶች።"
                        },
                        {
                            "verse": 9,
                            "text": "ከኢ​ዮ​አብ ልጆች የያ​ሔ​ኤል ልጅ አብ​ድያ፥ ከእ​ር​ሱም ጋር ሁለት መቶ ዐሥራ ስም​ንት ወን​ዶች።"
                        },
                        {
                            "verse": 10,
                            "text": "ከበ​ዐኛ ልጆች የዮ​ሴ​ፍያ ልጅ ሰሎ​ሚት፥ ከእ​ር​ሱም ጋር መቶ ስድሳ ወን​ዶች።"
                        },
                        {
                            "verse": 11,
                            "text": "ከቤ​ባይ ልጆች የቤ​ባይ ልጅ ዘካ​ር​ያስ፥ ከእ​ር​ሱም ጋር ሃያ ስም​ንት ወን​ዶች።"
                        },
                        {
                            "verse": 12,
                            "text": "ከዓ​ዝ​ጋድ ልጆች የአ​ቃ​ጦን ልጅ፤ ዮሓ​ናን፥ ከእ​ር​ሱም ጋር መቶ ዐሥር ወን​ዶች።"
                        },
                        {
                            "verse": 13,
                            "text": "ከኋ​ለ​ኞቹ ከአ​ዶ​ኒ​ቃም ልጆች ስማ​ቸው ይህ ነው፤ ኤሊ​ፋ​ልጥ፥ ይኢ​ኤል፥ ሰማ​አያ፥ ከእ​ነ​ር​ሱም ጋር ስድሳ ወን​ዶች።"
                        },
                        {
                            "verse": 14,
                            "text": "ከባ​ጎዊ ልጆች ውታ​ይና ዘቡድ፥ ከእ​ነ​ር​ሱም ጋር ሰባ ወን​ዶች።"
                        },
                        {
                            "verse": 15,
                            "text": "ወደ አኅ​ዋም ወደ​ሚ​ፈ​ስስ ወንዝ ሰበ​ሰ​ብ​ኋ​ቸው፤ በዚ​ያም ሦስት ቀን ሰፈ​ርን፤ ሕዝ​ቡ​ንና ካህ​ና​ቱ​ንም ስቈ​ጥ​ራ​ቸው በዚያ ከሌዊ ልጆች ማን​ንም አላ​ገ​ኘ​ሁም።"
                        },
                        {
                            "verse": 16,
                            "text": "ወደ አለ​ቆ​ቹም ወደ አል​ዓ​ዛር፥ ወደ አር​ኤል፥ ወደ ሰማ​አያ፥ ወደ ሀሎ​ናም፥ ወደ ያሪብ፥ ወደ ሄል​ና​ታን፥ ወደ ናታን፥ ወደ ዘካ​ር​ያስ፥ ወደ ሜሱ​ላም፥ ደግ​ሞም ወደ ዐዋ​ቂ​ዎቹ ወደ ዮያ​ሪ​ብና ወደ ሄል​ና​ታን ላክሁ።"
                        },
                        {
                            "verse": 17,
                            "text": "በካ​ሲ​ፍያ ስፍራ ወደ ነበ​ረው ወደ አለ​ቃው ወደ አዶ ላክ​ኋ​ቸው፤ ለአ​ም​ላ​ካ​ችን ቤትም አገ​ል​ጋ​ዮ​ችን ያመ​ጡ​ልን ዘንድ በካ​ሲ​ፍያ ስፍራ ለሚ​ኖ​ሩት ለአ​ዶና ለወ​ን​ድ​ሞቹ ለና​ታ​ኒም የሚ​ነ​ግ​ሩ​አ​ቸ​ውን በአ​ፋ​ቸው አደ​ረ​ግሁ።"
                        },
                        {
                            "verse": 18,
                            "text": "በላ​ያ​ች​ንም መል​ካም በሆ​ነው በአ​ም​ላ​ካ​ችን እጅ ከእ​ስ​ራ​ኤል ልጅ ከሌዊ ልጅ ከሞ​ሐሊ ልጆች ወገን የነ​በ​ረ​ውን አስ​ተ​ዋይ ሰው ሰራ​ብ​ያን፥ ከእ​ር​ሱም ጋር ዐሥራ ስም​ን​ቱን ልጆ​ቹ​ንና ወን​ድ​ሞ​ቹን አመ​ጡ​ልን።"
                        },
                        {
                            "verse": 19,
                            "text": "ደግ​ሞም አሴ​ብ​ያ​ስን፥ ከእ​ር​ሱም ጋር ከሜ​ራሪ ልጆች ወገን የነ​በ​ረ​ውን ኢሳ​ይ​ያ​ስን፥ ሃያ​ውን ወን​ድ​ሞ​ቹ​ንና ልጆ​ቻ​ቸ​ውን።"
                        },
                        {
                            "verse": 20,
                            "text": "ሌዋ​ው​ያ​ን​ንም እን​ዲ​ያ​ገ​ለ​ግሉ ዳዊ​ትና አለ​ቆቹ ከሰ​ጡ​አ​ቸው ናታ​ኒም ውስጥ ሁለት መቶ ሃያ ናታ​ኒ​ምን አመጡ፤ እነ​ዚ​ህም ሁሉ በስም በስ​ማ​ቸው ተሰ​በ​ሰቡ።"
                        },
                        {
                            "verse": 21,
                            "text": "በአ​ም​ላ​ካ​ችን ፊት ራሳ​ች​ንን እና​ዋ​ርድ ዘንድ፥ ከእ​ር​ሱም የቀ​ና​ውን መን​ገድ ለእ​ኛና ለል​ጆ​ቻ​ችን፥ ለን​ብ​ረ​ታ​ች​ንም ሁሉ እን​ለ​ምን ዘንድ በዚያ በአ​ኅዋ ወንዝ አጠ​ገብ ጾምን አወ​ጅሁ።"
                        },
                        {
                            "verse": 22,
                            "text": "ንጉ​ሡ​ንም፥ “የአ​ም​ላ​ካ​ችን እጅ በሚ​ሹት ሁሉ ላይ ለመ​ል​ካም ነው፤ ኀይ​ሉና ቍጣው ግን እር​ሱን በሚ​ተዉ ሁሉ ላይ ነው” ብለን ተና​ግ​ረን ነበ​ርና፤ በመ​ን​ገድ ካለው ጠላት ያድ​ኑን ዘንድ ጭፍ​ራና ፈረ​ሰ​ኞች ከን​ጉሡ እለ​ምን ዘንድ አፍሬ ነበ​ርና።"
                        },
                        {
                            "verse": 23,
                            "text": "ስለ​ዚ​ህም ነገር ጾምን፤ ወደ እግ​ዚ​አ​ብ​ሔ​ርም ለመ​ንን፤ እር​ሱ​ም​ሰ​ማን።"
                        },
                        {
                            "verse": 24,
                            "text": "ከካ​ህ​ና​ቱም አለ​ቆች ዐሥራ ሁለት ሰዎ​ችን፥ ሰራ​ብ​ያ​ንና ሐሳ​ብ​ያን፥ ከእ​ነ​ር​ሱም ጋር ዐሥር ወን​ድ​ሞ​ቻ​ቸ​ውን ለየሁ፤"
                        },
                        {
                            "verse": 25,
                            "text": "ንጉ​ሡና አማ​ካ​ሪ​ዎቹ፥ አለ​ቆ​ቹም፥ በዚ​ያም የተ​ገ​ኙት እስ​ራ​ኤል ሁሉ ያቀ​ረ​ቡ​ትን፥ ለአ​ም​ላ​ካ​ችን ቤት የቀ​ረ​በ​ውን ብሩ​ንና ወር​ቁን፥ ዕቃ​ው​ንም መዝኜ ሰጠ​ኋ​ቸው።"
                        },
                        {
                            "verse": 26,
                            "text": "ስድ​ስት መቶ አምሳ መክ​ሊት ብር፥ አንድ መቶም መክ​ሊት የብር ዕቃ​ዎች፥ አንድ መቶም መክ​ሊት ወርቅ፥"
                        },
                        {
                            "verse": 27,
                            "text": "ሃያም ባለ ሺህ ዳሪክ የወ​ርቅ ጽዋ​ዎች፥ ሁለ​ትም እንደ ወርቅ የከ​በሩ ከጥ​ሩና ከሚ​ያ​ን​ጸ​በ​ርቅ ናስ የተ​ሠሩ ዕቃ​ዎ​ችን መዝኜ በእ​ጃ​ቸው ሰጠሁ።"
                        },
                        {
                            "verse": 28,
                            "text": "እኔም “እና​ንተ ለእ​ግ​ዚ​አ​ብ​ሔር ተቀ​ድ​ሳ​ች​ኋል፤ ዕቃ​ዎ​ቹም ቅዱ​ሳን ናቸው፤ ብሩና ወር​ቁም ለአ​ባ​ቶ​ቻ​ችን አም​ላክ ለእ​ግ​ዚ​አ​ብ​ሔር በፈ​ቃድ የቀ​ረበ ነው፤"
                        },
                        {
                            "verse": 29,
                            "text": "በካ​ህ​ና​ትና በሌ​ዋ​ው​ያን አለ​ቆች፥ በእ​ስ​ራ​ኤ​ልም አባ​ቶች ቤቶች አለ​ቆች ፊት በኢ​የ​ሩ​ሳ​ሌም በእ​ግ​ዚ​አ​ብ​ሔር ቤት ጓዳ​ዎች ውስጥ እስ​ክ​ት​መ​ዝኑ ድረስ ተግ​ታ​ችሁ ጠብቁ” አል​ኋ​ቸው።"
                        },
                        {
                            "verse": 30,
                            "text": "ካህ​ና​ቱና ሌዋ​ው​ያ​ኑም ወደ ኢየ​ሩ​ሳ​ሌም ወደ አም​ላ​ካ​ችን ቤት ይወ​ስ​ዱት ዘንድ ብሩ​ንና ወር​ቁን፥ ዕቃ​ዎ​ቹ​ንም በሚ​ዛን ተቀ​በሉ።"
                        },
                        {
                            "verse": 31,
                            "text": "በመ​ጀ​መ​ሪ​ያ​ውም ወር በዐ​ሥራ ሁለ​ተ​ኛው ቀን ወደ ኢየ​ሩ​ሳ​ሌም እን​ሄድ ዘንድ ከአ​ኅዋ ወንዝ ተነ​ሣን፤ የአ​ም​ላ​ካ​ች​ንም እጅ በላ​ያ​ችን ነበረ፤ በመ​ን​ገ​ድም ከጠ​ላ​ትና ከሚ​ሸ​ምቅ ሰው እጅ አዳ​ነን።"
                        },
                        {
                            "verse": 32,
                            "text": "ወደ ኢየ​ሩ​ሳ​ሌ​ምም ደረ​ስን፤ በዚ​ያም ሦስት ቀን ተቀ​መ​ጥን።"
                        },
                        {
                            "verse": 33,
                            "text": "በአ​ራ​ተ​ኛ​ውም ቀን ብሩና ወርቁ፥ ዕቃ​ዎ​ቹም በአ​ም​ላ​ካ​ችን ቤት በካ​ህኑ በኦ​ርያ ልጅ በሜ​ሪ​ሞት እጅ ተመ​ዘኑ፤ ከእ​ር​ሱም ጋር የፊ​ን​ሐስ ልጅ አል​ዓ​ዛር ነበረ፤ ከእ​ነ​ር​ሱም ጋር ሌዋ​ው​ያን የኢ​ያሱ ልጅ ኢዮ​ዛ​ብ​ድና የቤ​ንዊ ልጅ ናሕ​ድያ ነበሩ።"
                        },
                        {
                            "verse": 34,
                            "text": "ሁሉም በቍ​ጥ​ርና በሚ​ዛን ተመ​ዘነ፤ ሚዛ​ኑም ሁሉ በዚያ ጊዜ ተጻፈ።"
                        },
                        {
                            "verse": 35,
                            "text": "ከም​ር​ኮም የወ​ጡት የም​ር​ኮ​ኞች ልጆች ለእ​ስ​ራ​ኤል አም​ላክ ለሚ​ቃ​ጠል መሥ​ዋ​ዕት ስለ እስ​ራ​ኤል ሁሉ ዐሥራ ሁለት ወይ​ፈ​ኖች፥ ዘጠና ስድ​ስ​ትም አውራ በጎች፥ ሰባ ሰባ​ትም ጠቦ​ቶች፥ ለኀ​ጢ​አት መሥ​ዋ​ዕት ዐሥራ ሁለት አውራ ፍየ​ሎ​ችን አቀ​ረቡ። ይህ ሁሉ ለእ​ግ​ዚ​አ​ብ​ሔር የሚ​ቃ​ጠል መሥ​ዋ​ዕት ነበረ።"
                        },
                        {
                            "verse": 36,
                            "text": "የን​ጉ​ሡ​ንም ትእ​ዛዝ በወ​ንዙ ማዶ ላሉት ለን​ጉሡ ሹሞ​ችና ገዢ​ዎች ሰጡ፤ እነ​ር​ሱም ሕዝ​ቡ​ንና የእ​ግ​ዚ​አ​ብ​ሔ​ርን ቤት አከ​በሩ።"
                        }
                    ]
                }
            ]
        },
        {
            "chapter": 9,
            "sections": [
                {
                    "title": "",
                    "verses": [
                        {
                            "verse": 1,
                            "text": "ይህም ከተ​ፈ​ጸመ በኋላ የሕ​ዝቡ አለ​ቆች ወደ እኔ ቀር​በው፥ “የእ​ስ​ራ​ኤል ሕዝብ ካህ​ና​ቱም፥ ሌዋ​ው​ያ​ኑም፥ እንደ ከነ​ዓ​ና​ው​ያን፥ እንደ ኬጤ​ዎ​ና​ው​ያን፥ እንደ ፌር​ዜ​ዎ​ና​ው​ያን፦ እንደ ኢያ​ቡ​ሴ​ዎ​ና​ው​ያን፥ እንደ አሞ​ና​ው​ያን፥ እንደ ሞዓ​ባ​ው​ያን፥ እንደ ግብ​ፃ​ው​ያ​ንና እንደ አሞ​ራ​ው​ያን ርኵ​ሰት ያደ​ር​ጋሉ እንጂ ከም​ድር አሕ​ዛብ አል​ተ​ለ​ዩም፤"
                        },
                        {
                            "verse": 2,
                            "text": "ለራ​ሳ​ቸ​ውና ለል​ጆ​ቻ​ቸ​ውም ሴቶች ልጆ​ቻ​ቸ​ውን ወስ​ደ​ዋል፤ የተ​ቀ​ደ​ሰ​ው​ንም ዘር ከም​ድር አሕ​ዛብ ጋር ደባ​ል​ቀ​ዋል፤ አስ​ቀ​ድ​ሞም አለ​ቆ​ቹና ሹሞቹ በዚህ መተ​ላ​ለፍ መጀ​መ​ሪያ ሆነ​ዋል” አሉኝ።"
                        },
                        {
                            "verse": 3,
                            "text": "ይህ​ንም ነገር በሰ​ማሁ ጊዜ ልብ​ሴ​ንና መጐ​ና​ጸ​ፊ​ያ​ዬን ቀደ​ድሁ፤ አዘ​ን​ሁም፤ የራ​ሴ​ንና የጢ​ሜ​ንም ጠጕር ነጨሁ፤ ደን​ግ​ጬም ተቀ​መ​ጥሁ።"
                        },
                        {
                            "verse": 4,
                            "text": "ስለ ምር​ኮ​ኞ​ቹም መተ​ላ​ለፍ የእ​ስ​ራ​ኤ​ልን አም​ላክ ቃል የሚ​ፈሩ ሁሉ ወደ እኔ ተሰ​በ​ሰቡ፤ እኔም እስከ ሠርክ መሥ​ዋ​ዕት ድረስ ዐዝኜ ተቀ​መ​ጥሁ።"
                        },
                        {
                            "verse": 5,
                            "text": "በሠ​ር​ክም መሥ​ዋ​ዕት ጊዜ ልብ​ሴና መጐ​ና​ጸ​ፊ​ያዬ እንደ ተቀ​ደደ ሆኖ ከመ​ዋ​ረዴ ተነ​ሣሁ፤ በጕ​ል​በ​ቴም ተን​በ​ር​ክኬ ወደ አም​ላኬ ወደ እግ​ዚ​አ​ብ​ሔር እጄን ዘረ​ጋሁ።"
                        },
                        {
                            "verse": 6,
                            "text": "እን​ዲ​ህም አልሁ፥ “አም​ላኬ ሆይ፥ ኀጢ​አ​ታ​ችን በራ​ሳ​ችን ላይ በዝ​ቶ​አ​ልና፥ በደ​ላ​ች​ንም ወደ ሰማይ ከፍ ብሎ​አ​ልና አም​ላኬ ሆይ፥ ፊቴን ወደ አንተ አነሣ ዘንድ አፍ​ራ​ለሁ፤ እፈ​ራ​ማ​ለሁ።"
                        },
                        {
                            "verse": 7,
                            "text": "ከአ​ባ​ቶ​ቻ​ችን ዘመን ጀም​ረን እስከ ዛሬ ድረስ እጅግ በድ​ለ​ናል፤ ስለ ኀጢ​አ​ታ​ችን እኛና ልጆ​ቻ​ችን"
                        },
                        {
                            "verse": 8,
                            "text": "አሁ​ንም ቅሬታ ይተ​ዉ​ልን ዘንድ፥ በተ​ቀ​ደ​ሰ​ውም ስፍ​ራው ኀይ​ልን"
                        },
                        {
                            "verse": 9,
                            "text": "ባሪ​ያ​ዎቹ ነንና፥ አም​ላ​ካ​ችን ግን በባ​ር​ነ​ታ​ችን አል​ተ​ወ​ንም፤ ቀለ​ባ​ች​ንን ይሰ​ጡን ዘንድ፥ የአ​ም​ላ​ካ​ች​ን​ንም ቤት ከፍ ከፍ ያደ​ርጉ ዘንድ፥ የተ​ፈ​ታ​ው​ንም ይጠ​ግኑ ዘንድ፥ በይ​ሁ​ዳና በኢ​የ​ሩ​ሳ​ሌ​ምም ቅጥር ያደ​ር​ጉ​ልን ዘንድ በፋ​ርስ ነገ​ሥ​ታት ፊት ሞገ​ስን ሰጠን።"
                        },
                        {
                            "verse": 10,
                            "text": "አሁ​ንስ ከዚህ በኋላ ምን እን​ላ​ለን? አም​ላ​ካ​ችን ሆይ፥ ትእ​ዛ​ዝ​ህን ትተ​ና​ልና።"
                        },
                        {
                            "verse": 11,
                            "text": "በባ​ሮ​ችህ በነ​ቢ​ያት እጅ ያዘ​ዝ​ሃ​ትን እን​ዲህ ስትል፦ ትወ​ር​ሱ​አት ዘንድ የም​ት​ገ​ቡ​ባት ምድር በም​ድር አሕ​ዛብ ርኵ​ሰት የረ​ከ​ሰች ናት፤ በር​ኵ​ሰ​ታ​ቸ​ውም ከዳር እስከ ዳር​ቻዋ ድረስ መል​ተ​ዋ​ታል።"
                        },
                        {
                            "verse": 12,
                            "text": "አሁ​ንም ትበ​ረቱ ዘንድ፥ የም​ድ​ሩ​ንም ፍሬ ትበሉ ዘንድ፥ ልጆ​ቻ​ች​ሁም ለዘ​ለ​ዓ​ለም ይወ​ር​ሱ​አት ዘንድ፥ ሴቶ​ችን ልጆ​ቻ​ች​ሁን ለወ​ን​ዶች ልጆ​ቻ​ቸው አት​ስጡ፤ ሴቶች ልጆ​ቻ​ቸ​ው​ንም ለወ​ን​ዶች ልጆ​ቻ​ችሁ አት​ው​ሰዱ፤ ሰላ​ማ​ቸ​ው​ንና ደኅ​ን​ነ​ታ​ቸ​ው​ንም ለዘ​ለ​ዓ​ለም አትሹ።"
                        },
                        {
                            "verse": 13,
                            "text": "ስለ ክፉ ሥራ​ች​ንና ስለ ታላቁ በደ​ላ​ችን ካገ​ኘን ነገር ሁሉ በኋላ፥ አንተ አም​ላ​ካ​ችን እንደ ኀጢ​አ​ታ​ችን ብዛት አል​ቀ​ሠ​ፍ​ኸ​ንም፤ ነገር ግን ድኅ​ነ​ትን ሰጠ​ኸን።"
                        },
                        {
                            "verse": 14,
                            "text": "ትእ​ዛ​ዝ​ህን እና​ፈ​ርስ ዘንድ ተመ​ል​ሰ​ና​ልና፥ ርኵስ ሥራ ከሚ​ሠሩ ከእ​ነ​ዚህ አሕ​ዛብ ጋርም ተጋ​ብ​ተ​ና​ልና ከእኛ ከሞት የሚ​ያ​መ​ልጥ እስ​ከ​ማ​ይ​ኖር ድረስ ፈጽ​መህ አት​ቈ​ጣን።"
                        },
                        {
                            "verse": 15,
                            "text": "አቤቱ የእ​ስ​ራ​ኤል አም​ላክ ሆይ፥ አንተ ጻድቅ ነህ፤ ዛሬም እንደ ሆነው እኛ አም​ል​ጠን ቀር​ተ​ናል፤ እነሆ በፊ​ትህ በበ​ደ​ላ​ችን አለን፤ ስለ​ዚህ በፊ​ትህ ሊቆም የሚ​ችል የለም።”"
                        }
                    ]
                }
            ]
        },
        {
            "chapter": 10,
            "sections": [
                {
                    "title": "ከባ​ዕ​ዳን ወገን የተ​ጋቡ የእ​ስ​ራ​ኤል ሰዎች እን​ዲ​ፋቱ ስለ ማድ​ረግ",
                    "verses": [
                        {
                            "verse": 1,
                            "text": "ዕዝ​ራም እያ​ለ​ቀ​ሰና በእ​ግ​ዚ​አ​ብ​ሔር ፊት እየ​ወ​ደቀ በጸ​ለ​የና በተ​ና​ዘዘ ጊዜ ከእ​ስ​ራ​ኤል ዘንድ የወ​ን​ድና የሴት፥ የሕ​ፃ​ና​ትም እጅግ ታላቅ ጉባኤ ወደ እርሱ ተሰ​በ​ሰበ፤ ሕዝ​ቡም እጅግ አለ​ቀሱ።"
                        },
                        {
                            "verse": 2,
                            "text": "ከኤ​ላም ልጆች ወገን የነ​በ​ረ​ውም የኢ​ያ​ሔል ልጅ ሴኬ​ንያ ዕዝ​ራን እን​ዲህ ብሎ ተና​ገ​ረው፥ “አም​ላ​ካ​ች​ንን በድ​ለ​ናል፤"
                        },
                        {
                            "verse": 3,
                            "text": "አሁ​ንም እንደ ጌታ​ዬና የአ​ም​ላ​ካ​ች​ንን ትእ​ዛዝ እን​ደ​ሚ​ፈ​ሩት ምክር፥ ሴቶ​ችን ሁሉ፥ ከእ​ነ​ር​ሱም የተ​ወ​ለ​ዱ​ትን እን​ሰ​ድድ ዘንድ ከአ​ም​ላ​ካ​ችን ጋር ቃል ኪዳን እና​ድ​ርግ። ተነሥ እንደ አም​ላ​ካ​ች​ንም ትእ​ዛዝ ገሥ​ፃ​ቸው፤ እንደ ሕጉም ያድ​ርጉ፤"
                        },
                        {
                            "verse": 4,
                            "text": "ይህም ነገር ለአ​ንተ ይገ​ባ​ልና፥ እኛም ከአ​ንተ ጋር ነንና ተነሣ፤ በርታ፤ አድ​ር​ገ​ውም።”"
                        },
                        {
                            "verse": 5,
                            "text": "ዕዝ​ራም ተነሣ፤ አለ​ቆ​ቹ​ንና ካህ​ና​ቱ​ንም፥ ሌዋ​ው​ያ​ኑ​ንም፥ እስ​ራ​ኤ​ልን ሁሉ እን​ደ​ዚህ ቃል ያደ​ርጉ ዘንድ አማ​ላ​ቸው፤ እነ​ር​ሱም ማሉ።"
                        },
                        {
                            "verse": 6,
                            "text": "ዕዝ​ራም ከእ​ግ​ዚ​አ​ብ​ሔር ቤት ፊት ተነ​ሥቶ ወደ ኤሊ​ያ​ሴብ ልጅ ወደ ዮሐ​ናን ጓዳ ገባ፤ ስለ ምር​ኮ​ኞ​ቹም ኀጢ​አት ያለ​ቅስ ነበ​ርና ገብቶ እን​ጀራ አል​በ​ላም፤ ውኃም አል​ጠ​ጣም።"
                        },
                        {
                            "verse": 7,
                            "text": "የም​ርኮ ልጆች ሁሉም ወደ ኢየ​ሩ​ሳ​ሌም ይሰ​በ​ሰቡ ዘንድ ወደ ይሁ​ዳና ወደ ኢየ​ሩ​ሳ​ሌም ዐዋጅ ነገረ"
                        },
                        {
                            "verse": 8,
                            "text": "“እስከ ሦስት ቀን ድረስ የማ​ይ​መጣ ሁሉ እንደ ሽማ​ግ​ሎ​ችና እን​ዳ​ለ​ቆች ምክር ከብቱ ሁሉ ይበ​ዝ​በዝ፤ እር​ሱም ከም​ር​ኮው ጉባኤ ይለይ” ብሎ ዐዋጅ አስ​ነ​ገረ።"
                        },
                        {
                            "verse": 9,
                            "text": "ሦስት ቀንም ሳያ​ልፍ በዘ​ጠ​ነ​ኛው ወር ከወ​ሩም በሃ​ያ​ኛው ቀን የይ​ሁ​ዳና የብ​ን​ያም ሰዎች ሁሉ በኢ​የ​ሩ​ሳ​ሌም ተሰ​በ​ሰቡ። ሕዝ​ቡም ሁሉ ስለ​ዚህ ነገ​ርና ስለ ታላቁ ዝናብ እየ​ተ​ን​ቀ​ጠ​ቀጡ በእ​ግ​ዚ​አ​ብ​ሔር ቤት ፊት ባለው አደ​ባ​ባይ ተቀ​መጡ።"
                        },
                        {
                            "verse": 10,
                            "text": "ካህ​ኑም ዕዝራ ተነ​ሥቶ፥ “ተላ​ል​ፋ​ች​ኋል፤ የእ​ስ​ራ​ኤ​ልን በደል ታበዙ ዘንድ እን​ግ​ዶ​ችን ሴቶች አግ​ብ​ታ​ች​ኋል።"
                        },
                        {
                            "verse": 11,
                            "text": "አሁ​ንም የአ​ባ​ቶ​ቻ​ች​ንን አም​ላክ እግ​ዚ​አ​ብ​ሔ​ርን አመ​ስ​ግኑ፤"
                        },
                        {
                            "verse": 12,
                            "text": "ጉባ​ኤ​ውም ሁሉ በታ​ላቅ ድምፅ መል​ሰው እን​ዲህ አሉ፥ “እንደ ተና​ገ​ር​ኸን እና​ደ​ርግ ዘንድ ይገ​ባ​ናል።"
                        },
                        {
                            "verse": 13,
                            "text": "ነገር ግን የሕ​ዝቡ ቍጥር ብዙ ነው፤ ጊዜ​ውም የት​ልቅ ዝናብ ጊዜ ነው፤ በሜ​ዳም ልን​ቆም አን​ች​ልም፤ በዚ​ህም ነገር እጅግ በድ​ለ​ና​ልና ይህ ሥራ የአ​ንድ ወይም የሁ​ለት ቀን ሥራ አይ​ደ​ለም።"
                        },
                        {
                            "verse": 14,
                            "text": "አለ​ቆ​ቻ​ች​ንም በጉ​ባ​ኤው ፋንታ ሁሉ ይቁሙ፤ ስለ​ዚ​ህም ነገር የአ​ም​ላ​ካ​ችን ጽኑ ቍጣ ከእኛ ይመ​ለስ ዘንድ እን​ግ​ዶ​ቹን ሴቶች ያገ​ቡት በከ​ተ​ሞ​ቻ​ችን ያሉት ሁሉ በተ​ቀ​ጠ​ረው ጊዜ ይምጡ፤ ከእ​ነ​ር​ሱም ጋር የከ​ተ​ማው ሁሉ ሽማ​ግ​ሌ​ዎ​ችና ፈራ​ጆች ይምጡ።”"
                        },
                        {
                            "verse": 15,
                            "text": "ነገር ግን የአ​ሣ​ሄል ልጅ ዮና​ታ​ንና የቴ​ቁዋ ልጅ የሐ​ዝያ ስለ​ዚህ ነገር ከእኔ ጋር ናቸው፤"
                        },
                        {
                            "verse": 16,
                            "text": "የስ​ደ​ተ​ኞ​ቹም ልጆች እን​ዲህ አደ​ረጉ፤ ካህኑ ዕዝራ፥ የአ​ባ​ቶ​ችም ቤቶች አለ​ቆች በየ​አ​ባ​ቶ​ቻ​ቸው ቤቶች ሁሉም በየ​ስ​ማ​ቸው ተለዩ፤ በዐ​ሥ​ረ​ኛ​ውም ወር በመ​ጀ​መ​ሪ​ያው ቀን ነገ​ሩን ይመ​ረ​ምሩ ዘንድ ተቀ​መጡ።"
                        },
                        {
                            "verse": 17,
                            "text": "እስከ መጀ​መ​ሪ​ያ​ውም ወር እስከ መጀ​መ​ሪ​ያው ቀን ድረስ ሠር​ተው እን​ግ​ዶ​ቹን ሴቶች ያገ​ቡ​ትን ሰዎች ሁሉ መር​ም​ረው ጨረሱ።"
                        },
                        {
                            "verse": 18,
                            "text": "ከካ​ህ​ና​ቱም ወገን ልጆች እን​ግ​ዶ​ቹን ሴቶች ያገቡ ሰዎች ተገኙ፤ ከኢ​ዮ​ሴ​ዴቅ ልጅ ከኢ​ያሱ ልጆ​ችና ከወ​ን​ድ​ሞቹ ማዓ​ሥያ፥ አል​ዓ​ዛር፥ ኦሬም፥ ገዳ​ልያ።"
                        },
                        {
                            "verse": 19,
                            "text": "ሚስ​ቶ​ቻ​ቸ​ውን ይፈቱ ዘንድ እጃ​ቸ​ውን ሰጡ፤ ስለ በደ​ላ​ቸ​ውም ከመ​ን​ጋው አንድ አውራ በግ ለበ​ደል መሥ​ዋ​ዕት አቀ​ረቡ።"
                        },
                        {
                            "verse": 20,
                            "text": "ከኢ​ሚር ልጆ​ችም አና​ኒና ዝብ​ድያ።"
                        },
                        {
                            "verse": 21,
                            "text": "ከኤ​ራም ልጆ​ችም መሳ​ሔል፥ ኤልያ፥ ሴሚያ፥ ያሔል፥ ዖዝያ።"
                        },
                        {
                            "verse": 22,
                            "text": "ከጳ​ሰ​ኮር ልጆ​ችም ኤል​ዮና፥ መሐ​ሰዓ፥ ይስ​ማ​ኤል፥ ናት​ና​ኤል፥ ኢዮ​ዛ​ባድ፥ ኤልሣ።"
                        },
                        {
                            "verse": 23,
                            "text": "ከሌ​ዋ​ው​ያ​ንም ኢዮ​ዛ​ባድ፥ ሰሜኢ፥ ቆሊ​ጣስ የሚ​ባል ቆልያ፥ ፈዲሓ፥ ይሁዳ፥ አል​ዓ​ዛር።"
                        },
                        {
                            "verse": 24,
                            "text": "ከመ​ዘ​ም​ራ​ንም ኤል​ያ​ሴብ፤ ከበ​ረ​ኞ​ችም ሰሎም፥ ጤሎም፥ ኡሪ።"
                        },
                        {
                            "verse": 25,
                            "text": "ከእ​ስ​ራ​ኤ​ልም ከፋ​ሮስ ልጆች ራምያ፥ ዖዝያ፥ መል​ክያ፥ ሚያ​ሚን፥ አል​ዓ​ዛር፥ መል​ክያ፥ ቤን​ያህ።"
                        },
                        {
                            "verse": 26,
                            "text": "ከኤ​ላም ልጆ​ችም መታ​ንያ፥ ዘካ​ር​ያስ፥ ኢያ​ኤል፥ አብዲ፥ ይሬ​ሞት፥ ኤልያ።"
                        },
                        {
                            "verse": 27,
                            "text": "ከዛቱ ልጆ​ችም ዔሊ​ዔ​ናይ፥ ኤል​ያ​ሴብ፥ መታ​ንያ፥ ኤር​ሞት፥ ዛባድ፥ ዓዚዛ።"
                        },
                        {
                            "verse": 28,
                            "text": "ከቤ​ባይ ልጆ​ችም ዮሐ​ናን፥ ሐና​ንያ፥ ዘባይ፥ አጥ​ላይ።"
                        },
                        {
                            "verse": 29,
                            "text": "ከባኒ ልጆ​ችም ሜሱ​ላም፥ መሉክ፥ ዓዳያ፥ ያሱብ፥ ሳዓል፥ ራሞት።"
                        },
                        {
                            "verse": 30,
                            "text": "ከፈ​ሐት ሞዓብ ልጆ​ችም ዓድና፥ ክላል፥ በና​ያስ፥ ማዕ​ሴያ፥ መታ​ንያ፥ ባስ​ል​ኤል፥ በነዊ፥ ምናሴ።"
                        },
                        {
                            "verse": 31,
                            "text": "ከኤ​ራም ልጆ​ችም አል​ዓ​ዛር፥ ይሲያ፥ ሚል​ክያ፥ ሰማያ፥ ስም​ዖን፥"
                        },
                        {
                            "verse": 32,
                            "text": "ብን​ያም፥ መሉክ፥ ሰማ​ርያ።"
                        },
                        {
                            "verse": 33,
                            "text": "ከሐ​ሱም ልጆ​ችም መታ​ንያ፥ መታታ፥ ዛባድ፥ ኤሊ​ፋ​ልጥ፥ ይሬ​ማይ፥ ምናሴ፥ ሰሜኢ።"
                        },
                        {
                            "verse": 34,
                            "text": "ከባኒ ልጆ​ችም ማዕ​ዳይ፥ ዓም​ራም፥ ኡኤል፥"
                        },
                        {
                            "verse": 35,
                            "text": "በና​ያስ፥ በዳያ፥ ኬል​ቅያ፥"
                        },
                        {
                            "verse": 36,
                            "text": "ውንያ፥ መሪ​ሙት፥ ኤል​ያ​ሴብ፤"
                        },
                        {
                            "verse": 37,
                            "text": "መታ​ንያ፥ መት​ናይ፥ የዕሡ፤"
                        },
                        {
                            "verse": 38,
                            "text": "የባ​ኔይ ልጆ​ችና የሰ​ሜይ ልጆች፤"
                        },
                        {
                            "verse": 39,
                            "text": "ሰሌ​ምያ፥ ናታን፥ ሐዳያ፤"
                        },
                        {
                            "verse": 40,
                            "text": "መክ​ነ​ድ​ባይ፥ ሴሴይ፥ ሰራይ፤"
                        },
                        {
                            "verse": 41,
                            "text": "ኤዛ​ር​ኤል፥ ሰሌ​ምያ፥ ሰማ​ርያ፥"
                        },
                        {
                            "verse": 42,
                            "text": "ሰሎም፥ አማ​ርያ፥ ዮሴፍ።"
                        },
                        {
                            "verse": 43,
                            "text": "ከናቡ ልጆ​ችም ይዒ​ኤል፥ መታ​ትያ፥ ዛባድ፥ ዛብ​ንያ፥ ያዳይ፥ ኢዮ​ኤል፥ በና​ያስ።"
                        },
                        {
                            "verse": 44,
                            "text": "እነ​ዚህ ሁሉ እን​ግ​ዶ​ቹን ሚስ​ቶች አግ​ብ​ተው ነበር፤ ከእ​ነ​ዚ​ህም ሚስ​ቶች ዐያ​ሌ​ዎቹ ልጆ​ችን ወል​ደው ነበር።"
                        }
                    ]
                }
            ]
        }
    ]
}
